{
    "speaker id frequency": {
        "3691": 1,
        "7055": 2,
        "6330": 2,
        "8193": 2,
        "303": 1,
        "8587": 1,
        "4335": 1,
        "7008": 2,
        "1028": 1,
        "3257": 1,
        "3314": 1,
        "6251": 1,
        "2292": 1,
        "1383": 1,
        "227": 2,
        "713": 1,
        "1571": 1,
        "98": 2,
        "150": 1,
        "548": 1,
        "6025": 1,
        "606": 1,
        "70": 1,
        "7148": 1,
        "7085": 3,
        "4481": 1,
        "7138": 1,
        "7117": 1,
        "6821": 1,
        "4681": 1,
        "4945": 1,
        "3869": 1,
        "948": 1,
        "4854": 1,
        "4122": 2,
        "1482": 1,
        "322": 2,
        "6341": 1,
        "7113": 1,
        "7480": 1,
        "5672": 1,
        "544": 1,
        "6406": 2,
        "2764": 1,
        "7956": 1,
        "6352": 1,
        "4297": 1,
        "2712": 1,
        "1826": 1,
        "8625": 1,
        "1379": 2,
        "5029": 1,
        "8113": 1,
        "4848": 1,
        "163": 2,
        "27": 1,
        "4991": 1,
        "7389": 1,
        "1384": 1,
        "8605": 2,
        "7498": 1,
        "1053": 3,
        "2751": 2,
        "6211": 1,
        "166": 2,
        "7067": 1,
        "4148": 1,
        "5186": 1,
        "1944": 2,
        "1392": 1,
        "7484": 2,
        "4936": 1,
        "5883": 1,
        "1593": 1,
        "726": 1,
        "7265": 1,
        "3513": 1,
        "6010": 1,
        "217": 3,
        "887": 1,
        "55": 1,
        "4280": 1,
        "3733": 1,
        "7994": 1,
        "6828": 1,
        "1811": 1,
        "1341": 1,
        "5043": 1,
        "7708": 1,
        "1335": 2,
        "5876": 1,
        "412": 1,
        "7434": 1,
        "340": 1,
        "114": 1,
        "7335": 1,
        "909": 2,
        "2201": 1,
        "5132": 1,
        "1845": 1,
        "211": 1,
        "1058": 1,
        "7569": 1,
        "4363": 1,
        "5062": 1,
        "696": 2,
        "8445": 1,
        "1752": 1,
        "7218": 1,
        "1235": 1,
        "2526": 1,
        "3274": 1,
        "3967": 4,
        "4898": 1,
        "57": 1,
        "246": 1,
        "460": 1,
        "2404": 1,
        "1754": 2,
        "7517": 1,
        "1353": 1,
        "8699": 1,
        "82": 1,
        "1387": 1,
        "1250": 1,
        "6224": 1,
        "8631": 1,
        "850": 1,
        "5060": 2,
        "7939": 1,
        "8474": 2,
        "3083": 2,
        "2269": 1,
        "7226": 1,
        "2562": 1,
        "6918": 1,
        "4205": 1,
        "4015": 1,
        "369": 2,
        "911": 2,
        "6733": 1,
        "7030": 1,
        "1367": 1,
        "253": 1,
        "5304": 1,
        "984": 1,
        "7302": 1,
        "3979": 1,
        "7657": 1,
        "7618": 1,
        "2834": 1,
        "5678": 1,
        "283": 1,
        "7011": 1,
        "6683": 1,
        "3187": 2,
        "2481": 1,
        "7286": 1,
        "2436": 1,
        "4836": 1,
        "1487": 1,
        "2491": 1,
        "6388": 2,
        "2638": 1,
        "128": 1,
        "2092": 2,
        "7240": 1,
        "4217": 1,
        "3361": 1,
        "8664": 1,
        "6351": 1,
        "4196": 1,
        "2911": 1,
        "5261": 1,
        "1445": 1,
        "3851": 1,
        "8444": 1,
        "1258": 1,
        "2893": 1,
        "3114": 1,
        "8337": 1,
        "188": 1,
        "1974": 1,
        "1116": 1,
        "1322": 1,
        "93": 1,
        "245": 1,
        "89": 1,
        "328": 1,
        "1859": 1,
        "666": 1,
        "254": 1,
        "7540": 2,
        "3647": 1,
        "1958": 1,
        "4853": 1,
        "806": 2,
        "3001": 1,
        "476": 1,
        "1260": 1,
        "8419": 1,
        "5867": 1,
        "32": 1,
        "8713": 1,
        "5513": 1,
        "4005": 1,
        "782": 1,
        "8051": 1,
        "23": 1,
        "6967": 1,
        "3983": 1,
        "446": 1,
        "3258": 1,
        "278": 1,
        "1027": 1,
        "2570": 1,
        "6518": 1,
        "2895": 1,
        "332": 1,
        "1776": 1,
        "3032": 1,
        "5911": 1,
        "1750": 1,
        "54": 1,
        "3879": 1,
        "957": 1,
        "4057": 1,
        "215": 1,
        "7348": 1,
        "1094": 1,
        "6258": 1,
        "2843": 1,
        "596": 1,
        "3928": 1,
        "470": 1,
        "1447": 1,
        "5049": 1,
        "8838": 1,
        "6209": 1,
        "2003": 1,
        "5825": 1,
        "5296": 1,
        "4063": 1,
        "731": 1,
        "3982": 1,
        "3347": 1,
        "2473": 1,
        "2816": 1,
        "4257": 1,
        "152": 1,
        "1841": 1,
        "730": 1,
        "2256": 1,
        "7756": 1,
        "225": 1,
        "4837": 1
    },
    "duration_per_speaker_min": {
        "23": 0.185,
        "27": 0.034,
        "32": 0.208,
        "54": 0.145,
        "55": 0.255,
        "57": 0.22,
        "70": 0.158,
        "82": 0.044,
        "89": 0.261,
        "93": 0.081,
        "98": 0.508,
        "114": 0.237,
        "128": 0.132,
        "150": 0.255,
        "152": 0.256,
        "163": 0.404,
        "166": 0.413,
        "188": 0.246,
        "211": 0.206,
        "215": 0.049,
        "217": 0.649,
        "225": 0.115,
        "227": 0.462,
        "245": 0.206,
        "246": 0.264,
        "253": 0.035,
        "254": 0.247,
        "278": 0.26,
        "283": 0.275,
        "303": 0.201,
        "322": 0.404,
        "328": 0.215,
        "332": 0.206,
        "340": 0.232,
        "369": 0.391,
        "412": 0.216,
        "446": 0.053,
        "460": 0.247,
        "470": 0.229,
        "476": 0.259,
        "544": 0.269,
        "548": 0.155,
        "596": 0.198,
        "606": 0.246,
        "666": 0.247,
        "696": 0.482,
        "713": 0.241,
        "726": 0.173,
        "730": 0.153,
        "731": 0.225,
        "782": 0.05,
        "806": 0.528,
        "850": 0.241,
        "887": 0.256,
        "909": 0.513,
        "911": 0.444,
        "948": 0.235,
        "957": 0.035,
        "984": 0.222,
        "1027": 0.238,
        "1028": 0.261,
        "1053": 0.71,
        "1058": 0.21,
        "1094": 0.236,
        "1116": 0.237,
        "1235": 0.251,
        "1250": 0.261,
        "1258": 0.261,
        "1260": 0.217,
        "1322": 0.258,
        "1335": 0.448,
        "1341": 0.159,
        "1353": 0.053,
        "1367": 0.241,
        "1379": 0.495,
        "1383": 0.228,
        "1384": 0.265,
        "1387": 0.209,
        "1392": 0.261,
        "1445": 0.237,
        "1447": 0.176,
        "1482": 0.221,
        "1487": 0.267,
        "1571": 0.207,
        "1593": 0.099,
        "1750": 0.211,
        "1752": 0.264,
        "1754": 0.515,
        "1776": 0.208,
        "1811": 0.225,
        "1826": 0.245,
        "1841": 0.205,
        "1845": 0.227,
        "1859": 0.23,
        "1944": 0.447,
        "1958": 0.247,
        "1974": 0.114,
        "2003": 0.064,
        "2092": 0.539,
        "2201": 0.251,
        "2256": 0.222,
        "2269": 0.222,
        "2292": 0.067,
        "2404": 0.221,
        "2436": 0.149,
        "2473": 0.208,
        "2481": 0.179,
        "2491": 0.244,
        "2526": 0.255,
        "2562": 0.223,
        "2570": 0.272,
        "2638": 0.046,
        "2712": 0.055,
        "2751": 0.518,
        "2764": 0.057,
        "2816": 0.238,
        "2834": 0.068,
        "2843": 0.231,
        "2893": 0.264,
        "2895": 0.262,
        "2911": 0.251,
        "3001": 0.243,
        "3032": 0.209,
        "3083": 0.246,
        "3114": 0.264,
        "3187": 0.486,
        "3257": 0.236,
        "3258": 0.21,
        "3274": 0.229,
        "3314": 0.189,
        "3347": 0.258,
        "3361": 0.238,
        "3513": 0.194,
        "3647": 0.117,
        "3691": 0.127,
        "3733": 0.135,
        "3851": 0.097,
        "3869": 0.268,
        "3879": 0.169,
        "3928": 0.231,
        "3967": 0.989,
        "3979": 0.253,
        "3982": 0.035,
        "3983": 0.262,
        "4005": 0.268,
        "4015": 0.035,
        "4057": 0.231,
        "4063": 0.259,
        "4122": 0.508,
        "4148": 0.178,
        "4196": 0.242,
        "4205": 0.255,
        "4217": 0.064,
        "4257": 0.241,
        "4280": 0.248,
        "4297": 0.236,
        "4335": 0.182,
        "4363": 0.066,
        "4481": 0.262,
        "4681": 0.255,
        "4836": 0.238,
        "4837": 0.199,
        "4848": 0.245,
        "4853": 0.243,
        "4854": 0.175,
        "4898": 0.244,
        "4936": 0.264,
        "4945": 0.221,
        "4991": 0.238,
        "5029": 0.258,
        "5043": 0.252,
        "5049": 0.202,
        "5060": 0.235,
        "5062": 0.256,
        "5132": 0.046,
        "5186": 0.209,
        "5261": 0.142,
        "5296": 0.148,
        "5304": 0.223,
        "5513": 0.174,
        "5672": 0.032,
        "5678": 0.249,
        "5825": 0.242,
        "5867": 0.247,
        "5876": 0.068,
        "5883": 0.221,
        "5911": 0.238,
        "6010": 0.202,
        "6025": 0.263,
        "6209": 0.075,
        "6211": 0.076,
        "6224": 0.257,
        "6251": 0.225,
        "6258": 0.215,
        "6330": 0.437,
        "6341": 0.196,
        "6351": 0.234,
        "6352": 0.077,
        "6388": 0.458,
        "6406": 0.474,
        "6518": 0.049,
        "6683": 0.272,
        "6733": 0.053,
        "6821": 0.253,
        "6828": 0.172,
        "6918": 0.234,
        "6967": 0.226,
        "7008": 0.513,
        "7011": 0.193,
        "7030": 0.226,
        "7055": 0.415,
        "7067": 0.257,
        "7085": 0.529,
        "7113": 0.262,
        "7117": 0.213,
        "7138": 0.083,
        "7148": 0.241,
        "7218": 0.246,
        "7226": 0.269,
        "7240": 0.253,
        "7265": 0.174,
        "7286": 0.26,
        "7302": 0.092,
        "7335": 0.239,
        "7348": 0.237,
        "7389": 0.259,
        "7434": 0.232,
        "7480": 0.213,
        "7484": 0.491,
        "7498": 0.221,
        "7517": 0.235,
        "7540": 0.466,
        "7569": 0.249,
        "7618": 0.206,
        "7657": 0.176,
        "7708": 0.095,
        "7756": 0.261,
        "7939": 0.235,
        "7956": 0.091,
        "7994": 0.113,
        "8051": 0.181,
        "8113": 0.054,
        "8193": 0.453,
        "8337": 0.087,
        "8419": 0.21,
        "8444": 0.238,
        "8445": 0.225,
        "8474": 0.494,
        "8587": 0.103,
        "8605": 0.424,
        "8625": 0.142,
        "8631": 0.266,
        "8664": 0.263,
        "8699": 0.221,
        "8713": 0.236,
        "8838": 0.257
    },
    "tokens": {
        "SHE": 55,
        "WAS": 151,
        "MERELY": 3,
        "A": 159,
        "PART": 4,
        "OF": 260,
        "MACHINE": 1,
        "THAT": 131,
        "RAN": 1,
        "ON": 59,
        "WITHOUT": 10,
        "SEEMING": 1,
        "TO": 272,
        "MAKE": 6,
        "ANY": 21,
        "IMPRESSION": 3,
        "THE": 564,
        "PRAIRIE'S": 1,
        "ENDLESSNESS": 1,
        "THERE": 31,
        "IS": 61,
        "LADY": 4,
        "JANE": 2,
        "BOLINGBROKE": 1,
        "WHO": 17,
        "BEAUTIFUL": 6,
        "AND": 319,
        "GOOD": 8,
        "ADMIRES": 1,
        "YOU": 68,
        "I": 122,
        "THINK": 7,
        "COULD": 38,
        "LEARN": 1,
        "SEEMED": 5,
        "KNOW": 15,
        "BY": 54,
        "INSTINCT": 2,
        "THINGS": 10,
        "RICHARD": 2,
        "NOT": 72,
        "UNDERSTAND": 6,
        "HE": 174,
        "HOW": 10,
        "CAME": 18,
        "IF": 23,
        "REACHED": 5,
        "OUT": 16,
        "HER": 56,
        "HANDS": 8,
        "TAKE": 10,
        "ANNABEL": 1,
        "FINGERS": 1,
        "THEMSELVES": 2,
        "THROUGH": 5,
        "DARKNESS": 2,
        "BLINDING": 1,
        "RAIN": 2,
        "BUT": 57,
        "WHERE": 11,
        "THEY": 60,
        "WERE": 32,
        "TELL": 7,
        "GAVE": 5,
        "UP": 12,
        "ALL": 36,
        "HOPE": 1,
        "LIFE": 9,
        "AT": 59,
        "LAST": 8,
        "TOUCHED": 1,
        "GROUND": 4,
        "WHEN": 38,
        "DAYLIGHT": 1,
        "WADED": 1,
        "SHORE": 3,
        "NIGHT": 6,
        "FOLLOWING": 2,
        "PRISONER'S": 1,
        "VISIT": 3,
        "AUDIENCE": 1,
        "CHAMBER": 2,
        "CONVERSATION": 2,
        "FINALLY": 2,
        "FELL": 7,
        "UPON": 22,
        "THIS": 57,
        "SUBJECT": 3,
        "EARS": 2,
        "INSTANT": 1,
        "HAD": 86,
        "FEARED": 1,
        "QUESTION": 8,
        "SOLA": 1,
        "RELATIVE": 1,
        "CAPTIVE": 1,
        "WHILE": 9,
        "GIVING": 1,
        "AN": 22,
        "ACCOUNT": 3,
        "BARBAROUS": 1,
        "CUSTOM": 1,
        "VERY": 27,
        "RELATION": 2,
        "WHICH": 48,
        "CHILLED": 1,
        "MY": 52,
        "BLOOD": 1,
        "LONG": 10,
        "AFTER": 23,
        "CANADA": 1,
        "WITH": 67,
        "VIEW": 2,
        "AS": 82,
        "IT": 100,
        "THOUGHT": 12,
        "SOME": 18,
        "FURTHER": 2,
        "TREACHERY": 1,
        "REJOINED": 1,
        "FRENCH": 1,
        "SHARP": 1,
        "CROSS": 3,
        "QUESTIONING": 1,
        "PUT": 6,
        "HIM": 54,
        "CONFUSION": 1,
        "FOUR": 3,
        "MEN": 12,
        "CARRIED": 6,
        "BIER": 1,
        "COVERED": 3,
        "BLACK": 2,
        "CLOTH": 2,
        "BEHIND": 4,
        "THEM": 29,
        "MAN": 21,
        "SHOVEL": 1,
        "HIS": 104,
        "SHOULDER": 2,
        "THIRD": 2,
        "LIGHTED": 1,
        "TORCH": 1,
        "HELD": 5,
        "READING": 2,
        "BOOK": 1,
        "PROBABLY": 1,
        "CHAPLAIN": 1,
        "CLOSED": 3,
        "PROCESSION": 2,
        "THEN": 22,
        "CHILDISH": 1,
        "PITY": 1,
        "BEGAN": 5,
        "CRYING": 3,
        "IN": 143,
        "EARNEST": 1,
        "ONLY": 17,
        "FIRST": 12,
        "MANY": 7,
        "FROM": 41,
        "LITTLE": 25,
        "MAID": 2,
        "FOR": 67,
        "OFTEN": 3,
        "OTTO'S": 1,
        "PRISON": 1,
        "LOOK": 6,
        "COMING": 6,
        "DAY": 16,
        "NEVER": 12,
        "SAW": 11,
        "COMMUNITY": 1,
        "PEOPLE": 8,
        "SO": 35,
        "HAPPY": 2,
        "OVER": 14,
        "ANYTHING": 6,
        "COLOURED": 1,
        "PROSPECT": 3,
        "NEW": 6,
        "BUILDING": 1,
        "ONE": 36,
        "WE": 29,
        "HOLDING": 2,
        "MEETING": 2,
        "SECURE": 1,
        "FUNDS": 1,
        "ITS": 13,
        "ERECTION": 1,
        "MARIA": 1,
        "SUPERINTENDED": 1,
        "DISTRIBUTION": 2,
        "BARMBRACK": 1,
        "EVERY": 12,
        "WOMAN": 7,
        "GOT": 6,
        "SLICES": 1,
        "GREAT": 17,
        "DEAL": 3,
        "LAUGHING": 1,
        "JOKING": 1,
        "DURING": 4,
        "MEAL": 2,
        "STILL": 6,
        "INTACT": 1,
        "AGED": 1,
        "HANDSOME": 1,
        "HOUSE": 8,
        "FAR": 7,
        "OFF": 2,
        "CALLED": 2,
        "TOM": 1,
        "ANYONE": 1,
        "HURT": 1,
        "NO": 36,
        "DAD": 1,
        "WE'RE": 1,
        "RIGHT": 9,
        "WHAT": 28,
        "HAPPENED": 3,
        "TEMPORAL": 1,
        "HEAD": 3,
        "REPUBLIC": 1,
        "WEST": 2,
        "SIMPLY": 2,
        "PAUSE": 2,
        "HERE": 10,
        "ASK": 3,
        "SINCERELY": 2,
        "REGRET": 1,
        "ABSENCE": 2,
        "WISH": 2,
        "POWER": 7,
        "SOLEMNLY": 1,
        "DECLARE": 1,
        "SUCH": 22,
        "CARELESSNESS": 1,
        "FUTURE": 1,
        "ATTRIBUTE": 1,
        "MUST": 7,
        "REMEMBER": 3,
        "DEAR": 5,
        "MOTHER": 7,
        "HAVE": 45,
        "CONSIDERED": 3,
        "MATTER": 3,
        "CERTAIN": 4,
        "DOUBTS": 2,
        "CONFESS": 3,
        "ARE": 38,
        "FAINTER": 1,
        "THAN": 9,
        "TRADER": 1,
        "TOLD": 6,
        "CAPTAIN": 2,
        "WOULD": 36,
        "GIVE": 11,
        "TWO": 13,
        "THOUSAND": 2,
        "DOLLARS": 3,
        "GET": 5,
        "CENT": 1,
        "BRING": 3,
        "BE": 47,
        "MUCH": 11,
        "LIKELY": 1,
        "SORT": 1,
        "SCRUPULOSITY": 1,
        "APOSTLE": 1,
        "COMMANDED": 2,
        "BELIEVERS": 1,
        "RESPECT": 1,
        "SPRANG": 1,
        "MORBID": 1,
        "TENDERNESS": 1,
        "CONSCIENCE": 1,
        "CENSORIOUSNESS": 1,
        "SPIRITUAL": 1,
        "PRIDE": 1,
        "PLACE": 10,
        "TILL": 4,
        "THREE": 10,
        "OR": 30,
        "DAYS": 6,
        "BEEN": 31,
        "SPENT": 2,
        "LEARNING": 1,
        "MOSTLY": 1,
        "WORN": 3,
        "CHAPERONE": 1,
        "PROVIDED": 1,
        "DRESS": 2,
        "NEWEST": 1,
        "FASHION": 2,
        "CATHERINE": 1,
        "TOO": 10,
        "MADE": 11,
        "PURCHASES": 1,
        "HERSELF": 3,
        "PRINCE": 4,
        "LOOKED": 11,
        "HOLE": 1,
        "WAY": 12,
        "BOTH": 8,
        "LEGS": 2,
        "INTO": 18,
        "SITTING": 3,
        "STONE": 3,
        "STOOPING": 1,
        "FORWARD": 3,
        "CORNER": 2,
        "REMAINED": 3,
        "OPEN": 1,
        "UNCOMFORTABLE": 1,
        "POSITION": 4,
        "ALLIES": 1,
        "RECONCILIATION": 1,
        "BETWEEN": 1,
        "SICILIANS": 1,
        "TOOK": 10,
        "PEACE": 2,
        "MISSUS": 14,
        "MOTT": 1,
        "JUBILANT": 1,
        "WORLD'S": 1,
        "INTEREST": 5,
        "GLAD": 4,
        "OPPORTUNITY": 3,
        "OCEAN": 1,
        "ENJOY": 1,
        "REST": 2,
        "PLEASURE": 1,
        "FRIENDS": 4,
        "WORKED": 1,
        "SAME": 9,
        "CAUSE": 4,
        "PARTY": 1,
        "ARRIVED": 3,
        "THEIR": 31,
        "ASTONISHMENT": 1,
        "TWENTY": 6,
        "MILES": 3,
        "AWAY": 9,
        "NEARER": 1,
        "FEATURE": 1,
        "DISTINCT": 1,
        "WHOLE": 7,
        "WONDERFUL": 2,
        "SHOW": 4,
        "SEEN": 4,
        "PROPORTIONS": 1,
        "LIKE": 12,
        "PAINTING": 2,
        "SKY": 1,
        "NAME": 7,
        "CANNOT": 5,
        "SINCE": 3,
        "PARENTS": 1,
        "ABANDONED": 1,
        "ME": 31,
        "THOUGH": 7,
        "OWN": 14,
        "POSSESSING": 1,
        "CAN": 11,
        "FATHER'S": 5,
        "THING": 6,
        "INSEPARABLE": 1,
        "ANOTHER": 8,
        "FACT": 4,
        "LAWS": 2,
        "PROPORTION": 1,
        "CLEARLY": 2,
        "PERCEIVED": 1,
        "IMAGINATIVELY": 1,
        "REALIZED": 1,
        "OUR": 19,
        "IDEAS": 3,
        "ALWAYS": 3,
        "JOINED": 1,
        "TOGETHER": 6,
        "NATURE": 7,
        "MONSTER": 1,
        "GOING": 2,
        "MEET": 1,
        "DERRELTON": 1,
        "STATION": 1,
        "FEW": 3,
        "SHORT": 6,
        "MINUTES": 1,
        "ONCE": 14,
        "DARK": 3,
        "BEETLING": 1,
        "BROWS": 1,
        "QUICK": 1,
        "FURTIVE": 1,
        "GLANCE": 1,
        "SEVENTEEN": 1,
        "WOMANLY": 1,
        "QUALITIES": 2,
        "DEVELOPED": 1,
        "ATMOSPHERE": 1,
        "UNINFLUENCED": 1,
        "SCHEMES": 1,
        "VAIN": 3,
        "SELFISH": 1,
        "UNCLE": 1,
        "JOHN": 2,
        "CASTING": 1,
        "ASIDE": 2,
        "MASK": 2,
        "POVERTY": 2,
        "RELIEF": 3,
        "GIRLS": 1,
        "GAZED": 1,
        "SCENE": 1,
        "RESPONDED": 1,
        "BRIGHT": 1,
        "EMOTIONS": 1,
        "CASE": 3,
        "HOWEVER": 5,
        "ALTHOUGH": 4,
        "OCCASION": 5,
        "ENTERTAINMENT": 3,
        "SIMILAR": 1,
        "COMPANY": 1,
        "STRIKINGLY": 1,
        "DISSIMILAR": 1,
        "INSTEAD": 1,
        "RUDE": 1,
        "MIXTURE": 2,
        "SAILORS": 1,
        "SOLDIERS": 2,
        "THOSE": 11,
        "BELONGING": 1,
        "HUMBLEST": 1,
        "GRADE": 1,
        "THESE": 18,
        "WORDS": 9,
        "SHOULD": 8,
        "SPOKEN": 2,
        "VOICE": 1,
        "BROKEN": 2,
        "WEAK": 1,
        "REPETITIONS": 1,
        "MINOR": 1,
        "DOORS": 3,
        "PRACTICE": 1,
        "HAS": 19,
        "SUPPOSE": 1,
        "REGULATED": 1,
        "ALMOST": 3,
        "ALTOGETHER": 2,
        "CONVENIENCE": 1,
        "SPECULATES": 1,
        "DOESN'T": 1,
        "WIN": 1,
        "COURSE": 2,
        "THROWS": 1,
        "BLAME": 1,
        "ELSE": 3,
        "CUR": 1,
        "COME": 10,
        "HIMSELF": 14,
        "SENDS": 1,
        "WIFE": 5,
        "CLAY": 1,
        "PRECEDING": 1,
        "WASHINGTON": 1,
        "NOW": 17,
        "ADDED": 2,
        "CORPS": 1,
        "WATCHERS": 1,
        "MISTER": 14,
        "HAWKINS": 1,
        "NONE": 2,
        "NEIGHBORLY": 1,
        "ASSISTANCE": 1,
        "OFFERED": 7,
        "OLD": 6,
        "GIVEN": 4,
        "DEFINITE": 1,
        "HOPES": 1,
        "EXPECTATIONS": 1,
        "EVEN": 13,
        "DESIRES": 1,
        "YET": 5,
        "MOMENT": 4,
        "APPREHENSION": 1,
        "UNKNOWN": 2,
        "CERTAINLY": 2,
        "FOUND": 8,
        "HEART": 5,
        "WORRYING": 1,
        "SOMETHING": 6,
        "QUITE": 5,
        "DIFFERENT": 3,
        "ABOVE": 3,
        "TRUTH": 3,
        "WHY": 3,
        "WONDER": 5,
        "ABOUT": 14,
        "LIVE": 3,
        "WALKING": 1,
        "FANGS": 1,
        "AWAITING": 1,
        "US": 10,
        "SOMEWHERE": 1,
        "AMONG": 5,
        "SILENT": 3,
        "TREES": 3,
        "PROOF": 1,
        "PARTS": 1,
        "SUBSTANCE": 3,
        "THUS": 5,
        "CONCEIVED": 1,
        "DIVIDED": 1,
        "EITHER": 5,
        "WILL": 19,
        "RETAIN": 1,
        "SPANIARDS": 1,
        "FURIOUS": 1,
        "CHARLES'S": 1,
        "APPEAR": 2,
        "SUCCESSFUL": 1,
        "QUAINT": 1,
        "RATHER": 3,
        "PITEOUS": 1,
        "FIGURE": 1,
        "DESTINED": 1,
        "MERRY": 1,
        "MONARCH": 1,
        "CATHARINE": 1,
        "PETITE": 1,
        "ISLAND": 4,
        "RIVER": 2,
        "KNEE": 1,
        "READ": 7,
        "WRIT": 1,
        "IRON": 1,
        "PEN": 2,
        "GOD": 3,
        "WEARIED": 1,
        "WESSEX": 1,
        "COUNTRY": 4,
        "FIELD": 5,
        "FEN": 1,
        "DEVILS": 1,
        "SEA": 2,
        "MOST": 10,
        "ACCEPTABLE": 1,
        "INTRODUCING": 1,
        "FATHER": 5,
        "SOON": 9,
        "RETURN": 4,
        "LETTER": 4,
        "DELIVERED": 1,
        "MISS": 5,
        "BENNET": 1,
        "COMMAND": 2,
        "COURTEOUS": 1,
        "PAPA": 1,
        "SAID": 36,
        "LOOKING": 6,
        "AFFECTIONATELY": 1,
        "FACE": 5,
        "WONDERING": 1,
        "TIME": 18,
        "POLITE": 1,
        "STEVENS": 1,
        "DOWN": 10,
        "UNDERGROUND": 1,
        "PALACE": 4,
        "DISAPPOINTED": 1,
        "EXPERIENCE": 2,
        "MANKIND": 1,
        "WENT": 14,
        "FORGOT": 1,
        "DISAGREEABLE": 3,
        "UPPER": 1,
        "WORLD": 8,
        "FEAR": 3,
        "REPLIED": 4,
        "SURREY": 1,
        "SPOKE": 2,
        "SLIGHT": 2,
        "NOISE": 1,
        "BURIED": 2,
        "LISTENER": 1,
        "CRIED": 4,
        "WYAT": 1,
        "GRASPING": 1,
        "SWORD": 1,
        "LEFT": 7,
        "SAY": 14,
        "AM": 9,
        "MYSELF": 10,
        "AGITATED": 1,
        "FEVERISH": 2,
        "SORTS": 1,
        "GO": 9,
        "TURN": 1,
        "GARDEN": 2,
        "RECOVER": 1,
        "DOCTOR": 1,
        "PRESSED": 2,
        "VALENTINE'S": 1,
        "HAND": 9,
        "VISITED": 1,
        "GRANDMOTHER": 1,
        "DESCENDED": 1,
        "STEPS": 3,
        "ROSES": 2,
        "GRAVE": 2,
        "BASKET": 3,
        "FLOWERS": 1,
        "SOFT": 3,
        "EVENING": 3,
        "BREEZE": 1,
        "MURMURED": 1,
        "BRANCHES": 2,
        "MAKING": 4,
        "ROSE": 2,
        "PLANTED": 1,
        "TREMBLE": 1,
        "OH": 3,
        "MARY": 1,
        "BIG": 2,
        "NEWS": 2,
        "ANIMAL": 2,
        "SOUL": 8,
        "WHOM": 2,
        "GAINED": 1,
        "ABSOLUTE": 1,
        "ASCENDANT": 1,
        "BURST": 2,
        "APARTMENT": 2,
        "ROBY": 1,
        "PLEASED": 1,
        "INTRIGUES": 1,
        "ADDICTED": 1,
        "AMUSEMENT": 1,
        "FOSTERING": 1,
        "LOVE": 4,
        "AFFAIRS": 1,
        "FOND": 1,
        "BEING": 10,
        "USEFUL": 1,
        "MATTERS": 3,
        "AVERSE": 1,
        "HAVING": 3,
        "PRESENTS": 1,
        "MARRIED": 2,
        "VULGAR": 1,
        "I'M": 1,
        "AFRAID": 1,
        "JUMP": 1,
        "BORNE": 1,
        "EXAMINATION": 2,
        "HUMAN": 4,
        "KNOWLEDGE": 3,
        "OCCUPIED": 1,
        "PREVIOUS": 2,
        "CHAPTERS": 1,
        "AMBITIOUS": 1,
        "ATTEMPTS": 1,
        "METAPHYSICIANS": 1,
        "PROCEEDED": 2,
        "ATTEMPT": 1,
        "PROVE": 1,
        "EVER": 9,
        "AGAIN": 18,
        "ALLUDE": 2,
        "BEFORE": 13,
        "LEAVE": 6,
        "YOUR": 10,
        "OUGHT": 2,
        "BETTER": 6,
        "SHELFER": 1,
        "VAUGHAN": 1,
        "DON'T": 5,
        "NOTHING": 11,
        "MORE": 15,
        "DELIGHTFUL": 3,
        "PLAIN": 1,
        "LIVING": 2,
        "BOWS": 1,
        "ALSO": 6,
        "BOARD": 1,
        "SHADOW": 1,
        "MOVES": 1,
        "LIPS": 1,
        "DOUBT": 3,
        "HEARD": 6,
        "SEE": 14,
        "SUN": 2,
        "RISES": 1,
        "GLORIOUS": 2,
        "SETS": 1,
        "UNCONSCIOUSLY": 1,
        "WIDE": 1,
        "ARC": 1,
        "PUSHED": 1,
        "ONWARDS": 1,
        "ALONG": 2,
        "RUGGED": 1,
        "SURFACE": 2,
        "ROCK": 4,
        "SUDDEN": 2,
        "FOOT": 2,
        "CONTACT": 1,
        "HARD": 2,
        "BENEATH": 2,
        "SNOW": 1,
        "MODERN": 2,
        "OWING": 2,
        "COMPLICATED": 1,
        "MECHANISM": 1,
        "FIRMAMENT": 1,
        "DETERMINED": 1,
        "MORALITIES": 1,
        "STAYED": 1,
        "THIRTY": 3,
        "MIND": 6,
        "REPEATED": 1,
        "CHILD": 4,
        "PONY": 2,
        "ROSAMOND": 1,
        "OGRE": 1,
        "POSSESSES": 1,
        "GREATER": 3,
        "AGILITY": 1,
        "COMPARISON": 1,
        "ANT": 1,
        "MOREOVER": 1,
        "REASON": 4,
        "MAKES": 1,
        "IMPOSSIBLE": 5,
        "RUN": 3,
        "CRAB": 1,
        "NEED": 4,
        "PRAISE": 1,
        "SCARCELY": 1,
        "OBSERVE": 1,
        "GUARD": 2,
        "NEITHER": 5,
        "AFFIRM": 1,
        "NOR": 5,
        "DENY": 2,
        "NEXT": 3,
        "IMPLICIT": 1,
        "ASSUMPTION": 1,
        "HIDE": 3,
        "CONSEQUENCES": 1,
        "SUSPECT": 1,
        "TEN": 1,
        "TIMES": 4,
        "WORSE": 1,
        "REALITY": 2,
        "CHILDREN": 2,
        "WELL": 14,
        "EYES": 7,
        "CAPABLE": 4,
        "FACING": 1,
        "ARRIVE": 1,
        "CHANGED": 1,
        "ORDERS": 1,
        "DIRECTIONS": 1,
        "BEHEADED": 1,
        "WITHIN": 4,
        "VERGE": 1,
        "TOWER": 1,
        "HUSBAND": 6,
        "LED": 3,
        "EXECUTION": 1,
        "WINDOW": 3,
        "TOKEN": 1,
        "REMEMBRANCE": 1,
        "MUSIC": 1,
        "STEALING": 1,
        "CLOSE": 2,
        "TOWARDS": 3,
        "SLEPT": 2,
        "WOKE": 1,
        "MORNING": 4,
        "BABY": 3,
        "GONE": 2,
        "HIGH": 2,
        "LOW": 1,
        "BUSY": 2,
        "LOOSE": 1,
        "CASH": 1,
        "OTHER": 9,
        "ARTICLES": 1,
        "BREECHES": 1,
        "POCKETS": 1,
        "YOUNG": 8,
        "SQUIRE": 4,
        "ENTERED": 2,
        "IRWINE": 2,
        "SIDE": 9,
        "STOOD": 5,
        "HOMAGE": 1,
        "AGREEABLE": 1,
        "ARTHUR": 1,
        "LIKED": 1,
        "FEEL": 4,
        "IMPORTANCE": 1,
        "DETESTABLE": 1,
        "BLOT": 1,
        "STARS": 1,
        "KNEW": 8,
        "DO": 21,
        "SAT": 6,
        "WEEP": 1,
        "DWARF": 1,
        "OPENED": 4,
        "DOOR": 6,
        "TASK": 5,
        "RING": 1,
        "FINGER": 1,
        "ILLUSIONS": 1,
        "FORMER": 2,
        "CLASS": 1,
        "DIDN'T": 1,
        "EXIST": 1,
        "STEERED": 1,
        "DECISIONS": 1,
        "EMPLOYED": 1,
        "DIRECTED": 2,
        "STIMULATED": 1,
        "ASSOCIATES": 1,
        "OWNERS": 1,
        "AMERICA": 1,
        "REAL": 1,
        "RESPONSIBLE": 1,
        "CITIZENS": 1,
        "RATE": 1,
        "CONCLUSION": 1,
        "SHORTLY": 1,
        "LADIES": 2,
        "DRAWING": 1,
        "ROOM": 5,
        "BADE": 1,
        "OWEN": 1,
        "GOVERNED": 1,
        "LIVES": 2,
        "LAW": 3,
        "OPINION": 5,
        "RULE": 1,
        "APPLY": 1,
        "INTENTION": 1,
        "ACTS": 2,
        "JOSEPH": 1,
        "COLLINS": 1,
        "ADDITIONAL": 1,
        "PATIENT": 1,
        "JOE": 1,
        "REALLY": 3,
        "SPECIES": 1,
        "MECHANICAL": 1,
        "OURSELVES": 2,
        "CHIEF": 3,
        "OPERATIONS": 1,
        "RELATIONS": 2,
        "COMPARISONS": 1,
        "PROPER": 2,
        "OBJECTS": 1,
        "ACTING": 2,
        "CONSEQUENCE": 1,
        "CONNECTED": 2,
        "DETAILS": 1,
        "CONNECTION": 1,
        "LINKS": 1,
        "MISSING": 1,
        "DISCERNMENT": 1,
        "GROSS": 1,
        "WALKED": 4,
        "QUICKLY": 1,
        "OBLIGED": 2,
        "JUST": 7,
        "INCLINED": 1,
        "MIDDLE": 1,
        "MET": 2,
        "PARSON": 1,
        "PARISH": 1,
        "NEAR": 1,
        "DECIDED": 1,
        "MAJORITY": 2,
        "SERIOUS": 1,
        "REGARDED": 1,
        "WONDERS": 1,
        "BILLY": 1,
        "INCREASED": 1,
        "FULLY": 1,
        "HISTORY": 1,
        "RECEIVED": 6,
        "THEATRE": 1,
        "TERRIBLE": 1,
        "TRAGEDY": 1,
        "CLOUDINESS": 1,
        "INSANITY": 1,
        "ANTAGONISM": 1,
        "BACK": 11,
        "REFUGE": 1,
        "DOGGED": 1,
        "SILENCE": 4,
        "THEREFORE": 2,
        "CRY": 1,
        "EDUCATION": 1,
        "GRAY": 1,
        "DID": 11,
        "CARE": 4,
        "HORNER": 1,
        "ENOUGH": 4,
        "FAMILY": 1,
        "EARTHLY": 1,
        "TOWN": 3,
        "COUNSELLOR": 1,
        "CLEVER": 2,
        "REASSURED": 1,
        "SORCERER": 1,
        "BAGPIPER": 1,
        "SPEAKS": 1,
        "SENT": 1,
        "HORRIBLE": 1,
        "VERMIN": 1,
        "CIRCUMSTANCES": 5,
        "PERMITTING": 1,
        "REGARD": 1,
        "SEASONS": 1,
        "BUSINESS": 4,
        "ASSISTANT": 1,
        "NOTE": 1,
        "CLOCKS": 1,
        "WRITE": 2,
        "OBSERVATIONS": 1,
        "DICTATIONS": 1,
        "SMILED": 5,
        "AVOWAL": 1,
        "SOMEWHAT": 1,
        "DISEASE": 1,
        "MAY": 9,
        "SICKENED": 1,
        "BODY": 5,
        "SHOCK": 1,
        "RESTFUL": 1,
        "FLAME": 2,
        "FRIEND'S": 1,
        "SOFTLY": 1,
        "WARMS": 1,
        "BURNING": 2,
        "EVERYTHING": 3,
        "EVIDENCE": 1,
        "VIOLENT": 1,
        "DESPERATE": 2,
        "STRUGGLE": 1,
        "D'ARTAGNAN": 4,
        "FANCIED": 2,
        "RECOGNIZE": 1,
        "AMID": 1,
        "STRANGE": 2,
        "DISORDER": 2,
        "FRAGMENTS": 1,
        "GARMENTS": 1,
        "BLOODY": 1,
        "SPOTS": 1,
        "STAINING": 1,
        "CURTAINS": 1,
        "AIR": 4,
        "CLEAR": 2,
        "NORTH": 1,
        "WIND": 2,
        "BLEW": 1,
        "STEADILY": 1,
        "STAND": 3,
        "AGAINST": 2,
        "HANS": 1,
        "TAKEN": 3,
        "SIGN": 1,
        "ENDED": 1,
        "SHOOK": 2,
        "ANNOUNCED": 1,
        "MEAN": 3,
        "IMPORTANT": 3,
        "THOROUGHFARES": 1,
        "CITY": 1,
        "PARIS": 2,
        "SPECULATION": 1,
        "PROPOSES": 1,
        "MONEY": 6,
        "DISPOSES": 1,
        "DIFFICULTY": 3,
        "NEWLY": 1,
        "NAMED": 2,
        "STREET": 2,
        "DIED": 2,
        "BIRTH": 1,
        "CURE": 1,
        "DOES": 4,
        "PIECE": 2,
        "IMPUDENCE": 1,
        "FOOL": 1,
        "CARDINAL": 1,
        "EAGER": 1,
        "AFFECTED": 1,
        "SHYNESS": 1,
        "EXPOSTULATED": 1,
        "OPENNESS": 1,
        "EASINESS": 1,
        "ESTIMATE": 1,
        "TOTAL": 1,
        "SELLING": 1,
        "VALUE": 1,
        "HELPLESS": 1,
        "DEVOTES": 1,
        "BEG": 1,
        "WORK": 8,
        "FARM": 2,
        "TRY": 3,
        "EARN": 1,
        "WOULDN'T": 2,
        "MINDED": 1,
        "SECOND": 2,
        "OMNIPOTENCE": 1,
        "DAYES": 3,
        "PAST": 3,
        "COMPUTE": 1,
        "HEAV'N": 1,
        "MICHAEL": 1,
        "POWERS": 3,
        "FORTH": 1,
        "TAME": 1,
        "DISOBEDIENT": 1,
        "YES": 6,
        "MASTER": 4,
        "SIR": 4,
        "THOMAS": 1,
        "HAWERBURCH": 1,
        "SHUDDERED": 1,
        "FAILED": 1,
        "ASSEMBLE": 1,
        "NUMBERS": 2,
        "ALLOWED": 1,
        "CHOOSE": 1,
        "OBEDIENCE": 2,
        "STRANGER": 1,
        "ACCOSTED": 1,
        "OBJECT": 4,
        "CHOICE": 2,
        "PRESENT": 3,
        "PIECES": 1,
        "CRISP": 1,
        "LISTENED": 3,
        "SURPRISED": 1,
        "GIRL'S": 1,
        "DESCRIPTION": 1,
        "HUMOR": 1,
        "PEPPER": 1,
        "SALT": 1,
        "BUTTER": 1,
        "EACH": 3,
        "CUTLETS": 1,
        "COVER": 1,
        "CREPINETTE": 1,
        "BROIL": 1,
        "FRY": 1,
        "LIGHT": 4,
        "BROWN": 1,
        "WHOSE": 3,
        "EVIL": 2,
        "TONGUE": 2,
        "KNOWN": 2,
        "DUSTY": 1,
        "FRAYED": 1,
        "COAT": 1,
        "EVIDENTLY": 2,
        "COMMON": 2,
        "MESSENGER": 1,
        "GENTLEMEN": 2,
        "BLOUNT": 1,
        "ASKED": 4,
        "DOUBTFULLY": 1,
        "DAISY": 1,
        "TURNED": 6,
        "HOUSTONIA": 1,
        "SCORNFULLY": 1,
        "LAUGHED": 1,
        "DANCED": 1,
        "SLENDER": 1,
        "STEM": 1,
        "COWSLIP": 1,
        "BENT": 1,
        "RIPPLING": 2,
        "WAVES": 1,
        "WHISPERED": 1,
        "TALE": 2,
        "EXCLAIMED": 4,
        "HURRIEDLY": 1,
        "CLOSING": 1,
        "ANNE": 1,
        "AUSTRIA": 1,
        "RAISED": 2,
        "UNMOVED": 1,
        "SUAVITY": 1,
        "MANNER": 4,
        "BELIEVE": 5,
        "UNDERSTANDING": 1,
        "APPEARED": 3,
        "COMPEERS": 1,
        "MANIFESTED": 1,
        "PURPOSE": 2,
        "ADHERING": 1,
        "RIGIDLY": 1,
        "TEXT": 1,
        "EXTENSIVE": 1,
        "SHADES": 1,
        "TWILIGHT": 1,
        "BEGINNING": 3,
        "SETTLE": 1,
        "EARTH": 2,
        "OLIVER": 1,
        "INTENT": 1,
        "BOOKS": 2,
        "PORING": 1,
        "CARRYING": 1,
        "CONSCIOUSNESS": 2,
        "PRINCE'S": 1,
        "ENTER": 2,
        "INFORM": 1,
        "COBBLER": 1,
        "DESERTED": 1,
        "SEES": 1,
        "PERSON": 2,
        "INFERENCE": 1,
        "CAPACITY": 1,
        "MAGISTRATE": 1,
        "UNDER": 3,
        "LAY": 5,
        "OFFICE": 1,
        "APT": 1,
        "INTERESTED": 2,
        "HAZARD": 1,
        "MATERIAL": 2,
        "CENSURE": 1,
        "PERPLEXITY": 1,
        "NEARLY": 2,
        "RE": 1,
        "ESTABLISHED": 1,
        "REGULATION": 1,
        "REASONS": 2,
        "JUSTIFY": 1,
        "DRAWBACKS": 1,
        "EXPORTING": 1,
        "GOODS": 1,
        "COUNTRIES": 1,
        "FOREIGN": 2,
        "INDEPENDENT": 1,
        "MERCHANTS": 1,
        "MANUFACTURERS": 1,
        "INDICATIONS": 1,
        "DIE": 2,
        "INSTANTLY": 2,
        "STAGGERED": 1,
        "CLUTCHING": 2,
        "WOUND": 1,
        "SHALL": 6,
        "PERFORM": 2,
        "AUTOPSY": 1,
        "DUNDEE": 1,
        "CROSSED": 1,
        "STEPPING": 1,
        "DEAD": 3,
        "MAN'S": 1,
        "STICK": 2,
        "CONTENT": 1,
        "BEST": 7,
        "PROVOKED": 1,
        "APPEARS": 1,
        "BADLY": 1,
        "CHOSEN": 1,
        "WHEELS": 2,
        "HOLD": 1,
        "WOOL": 1,
        "SPOOLS": 1,
        "QUEEN'S": 1,
        "DYER": 1,
        "POEM": 1,
        "UTTERANCES": 1,
        "ARDENT": 2,
        "WHIG": 1,
        "EARNESTLY": 2,
        "ADVOCATING": 1,
        "ELECTION": 2,
        "TIPPECANOE": 1,
        "UNWILLING": 1,
        "DOING": 1,
        "CAPITAL": 1,
        "SPECIMEN": 1,
        "ELOQUENCE": 1,
        "HEALTHY": 1,
        "CONDITIONS": 1,
        "ENGLISH": 2,
        "BREED": 1,
        "MISTAKE": 1,
        "POSSIBLY": 2,
        "VAN": 1,
        "BRANDT'S": 1,
        "GRADUALLY": 1,
        "WORTH": 4,
        "LIE": 2,
        "FAINT": 1,
        "CHANCE": 2,
        "ABLE": 4,
        "UNDO": 1,
        "TRIUMPHANTLY": 1,
        "IMPULSIVE": 1,
        "UNREASONING": 1,
        "ACTION": 1,
        "WAVE": 2,
        "FEET": 3,
        "DEEP": 3,
        "MIGHTY": 1,
        "FORCE": 2,
        "SWIFTNESS": 1,
        "TOWARD": 2,
        "BREATH": 1,
        "SPOT": 1,
        "SIDEWALK": 1,
        "FLANTON": 1,
        "DOG": 1,
        "PAUSED": 1,
        "POKED": 1,
        "BOY": 5,
        "PASSING": 3,
        "SWING": 2,
        "SEATED": 2,
        "WEEPING": 1,
        "BITTERLY": 3,
        "HURRYING": 1,
        "FARMER": 2,
        "CARRY": 2,
        "HOME": 6,
        "CALF": 1,
        "STEAD": 1,
        "IMMEDIATELY": 3,
        "ORDER": 3,
        "ANGEL": 1,
        "ESTEEMED": 1,
        "CORRUPT": 1,
        "HARDLY": 3,
        "PURITY": 1,
        "TRIAL": 2,
        "TEMPTATION": 2,
        "EDITOR": 1,
        "LIBERATOR": 1,
        "PROMISE": 1,
        "THEREAFTER": 1,
        "KINDLY": 1,
        "DISPOSED": 2,
        "WRITING": 1,
        "UNIVERSAL": 1,
        "MILITARY": 1,
        "TRAINING": 1,
        "LISTEN": 3,
        "WON'T": 1,
        "SON": 2,
        "YOUTH": 1,
        "TURNING": 2,
        "APPRECIATE": 1,
        "KEEPS": 1,
        "WARM": 1,
        "FIRES": 1,
        "WIMBUSH": 1,
        "GOES": 3,
        "CALENDAR": 1,
        "TEMPERATURE": 2,
        "WEATHER": 3,
        "KNOWS": 3,
        "PRINCESS": 2,
        "EASILY": 2,
        "HEATED": 1,
        "FORM": 2,
        "SCULPTURE": 1,
        "WONDERFULLY": 1,
        "ADORNED": 1,
        "ENLIVENED": 1,
        "GLACIERS": 1,
        "WATERFALLS": 1,
        "THROUGHOUT": 1,
        "EXTENT": 1,
        "FLOOR": 2,
        "FLOWERY": 1,
        "LANDSCAPE": 1,
        "YOSEMITE": 1,
        "KIRSTY'S": 1,
        "AUTHORITY": 1,
        "EQUAL": 3,
        "HERS": 1,
        "COMPELLED": 2,
        "WATCHED": 1,
        "ESCAPE": 1,
        "KIRSTY": 1,
        "MIGHT": 8,
        "RESERVED": 1,
        "TENDER": 1,
        "KEPT": 2,
        "HIDDEN": 1,
        "SCRUPULOUSLY": 1,
        "EASY": 2,
        "ACQUAINTED": 2,
        "PAUL": 1,
        "UNTIL": 3,
        "WALK": 1,
        "BOOKSTORE": 1,
        "BUY": 1,
        "SEVEN": 1,
        "SHILLINGS": 1,
        "WORKS": 1,
        "HUMOROUS": 1,
        "CHARACTER": 3,
        "YEARS": 3,
        "PRINT": 1,
        "COMPOSITORS": 1,
        "SUFFOCATED": 1,
        "LAUGHTER": 1,
        "GASPING": 1,
        "SCIENCE": 1,
        "STRENGTH": 6,
        "EXERCISE": 2,
        "EXISTENCE": 3,
        "HEAVIER": 1,
        "PLANET": 1,
        "BECAUSE": 3,
        "LABOR'D": 1,
        "WISELY": 1,
        "STATES": 3,
        "TRYING": 2,
        "PERIOD": 2,
        "PARTURITION": 1,
        "SEEDS": 1,
        "SEEMS": 1,
        "DARE": 1,
        "UNION": 3,
        "OWNING": 1,
        "ENJOYING": 1,
        "MADAM": 2,
        "LET": 5,
        "POINT": 2,
        "PRESENTLY": 3,
        "CONTINUED": 2,
        "SUMMER": 1,
        "FINE": 2,
        "INTERVALS": 1,
        "CONSIDER": 1,
        "ADVANTAGES": 1,
        "POND": 2,
        "STREAMS": 1,
        "TORRENTS": 1,
        "UNDERSTOOD": 2,
        "PUTTING": 2,
        "DRAWER": 1,
        "MAXINEFF": 1,
        "SURE": 2,
        "CHANGE": 3,
        "READILY": 1,
        "INCREASE": 1,
        "SUSPENSE": 1,
        "UNBEARABLE": 1,
        "CAGLIOSTRO": 1,
        "COVERING": 1,
        "CUT": 2,
        "SET": 2,
        "ENDURANCE": 1,
        "SHUT": 1,
        "SIGHT": 3,
        "FLESH": 1,
        "DEVIL": 1,
        "FIGHT": 1,
        "TEMPTATIONS": 1,
        "GUESS": 1,
        "IMBECILITY": 1,
        "GOVERNMENT": 2,
        "DISCORD": 1,
        "PROVINCES": 1,
        "INFLUENCE": 1,
        "INDIGNITIES": 1,
        "PRECARIOUS": 1,
        "PECULIAR": 1,
        "CALAMITIES": 1,
        "WAR": 1,
        "INTERPOSE": 1,
        "CONQUERED": 1,
        "FEARS": 1,
        "FRIEND": 2,
        "THOU": 4,
        "HAST": 2,
        "WISHED": 1,
        "DISTURBED": 1,
        "NARROW": 1,
        "PASSAGE": 2,
        "STRETCHED": 1,
        "FRONT": 1,
        "INDEED": 7,
        "SIMPLICITY": 2,
        "AMELIA": 1,
        "VOID": 1,
        "SUSPICION": 1,
        "BETRAYED": 2,
        "AFTERNOON": 2,
        "DRINKING": 1,
        "TEA": 1,
        "SENSATION": 1,
        "EXPERIENCED": 1,
        "SURPRISE": 3,
        "THIRSTY": 1,
        "ACTUALLY": 1,
        "RUNNING": 1,
        "STREAM": 1,
        "FLOWED": 1,
        "WAVELETS": 1,
        "SATISFACTORY": 1,
        "REPLY": 1,
        "LEAST": 4,
        "BAD": 2,
        "TASTE": 1,
        "EVOKE": 1,
        "IMPERFECTLY": 1,
        "HESITATINGLY": 1,
        "COMPULSION": 2,
        "SMALL": 3,
        "GODSENDS": 1,
        "GLORIFICATIONS": 1,
        "UNLESS": 2,
        "FATE": 1,
        "DESIRED": 1,
        "LIBERTY": 3,
        "INCLINATION": 1,
        "SHIFT": 1,
        "EXIGENCIES": 1,
        "SUSCEPTIBLE": 1,
        "LIMITATION": 1,
        "LAYING": 1,
        "TAXES": 1,
        "UNCONFINED": 1,
        "REVENUE": 1,
        "REQUISITE": 1,
        "PURPOSES": 1,
        "LOCAL": 1,
        "ADMINISTRATIONS": 2,
        "AWOKE": 2,
        "MORROW": 1,
        "ROUSED": 1,
        "SLEEP": 2,
        "LOVELINESS": 1,
        "CHARMS": 1,
        "EXPRESS": 2,
        "HELP": 2,
        "ACCOMPLISH": 1,
        "BEHAVIOR": 1,
        "WILDLY": 1,
        "ROBBERS": 1,
        "EXAMINE": 2,
        "CAVE": 1,
        "BAGS": 1,
        "CASSIM": 2,
        "BROUGHT": 3,
        "READY": 3,
        "LOAD": 1,
        "MULES": 1,
        "PLACES": 1,
        "ALI": 1,
        "BABA": 1,
        "FELT": 5,
        "SHAKEN": 1,
        "EDMUND": 1,
        "MEANT": 1,
        "LOSE": 2,
        "FORGET": 2,
        "FORGOTTEN": 1,
        "THOUGHTFULLY": 2,
        "TRAIL": 2,
        "LENA": 1,
        "SPEAKING": 1,
        "NERVOUSLY": 1,
        "WANTED": 2,
        "PARTICULARLY": 1,
        "ADVICE": 1,
        "NUMBER": 2,
        "ISLANDS": 1,
        "LABYRINTH": 1,
        "CHANNELS": 1,
        "EAST": 1,
        "MISSISSIPPI": 1,
        "FIND": 5,
        "PRACTICALLY": 1,
        "LATTER": 3,
        "DOUBTLESS": 1,
        "PROCEED": 1,
        "SEVERAL": 1,
        "BELOW": 1,
        "MOUTH": 1,
        "CASES": 1,
        "INSTANCES": 1,
        "BODILY": 1,
        "REMOVED": 2,
        "MORLOCKS": 1,
        "JUDGED": 1,
        "THICK": 1,
        "DUST": 1,
        "DEADENED": 1,
        "FOOTSTEPS": 1,
        "WEENA": 1,
        "PATH": 2,
        "RUNS": 1,
        "BESIDE": 2,
        "WOOD": 2,
        "REIN": 1,
        "MARE": 1,
        "RODE": 4,
        "CHATTING": 1,
        "MERRILY": 1,
        "NOOK": 1,
        "APPLE": 3,
        "ORCHARD": 1,
        "AGO": 1,
        "GIRL": 4,
        "PLAYING": 1,
        "BALL": 1,
        "ROUND": 1,
        "ASSEMBLY": 1,
        "FIXED": 1,
        "TRUE": 1,
        "EAGERNESS": 1,
        "BITTERNESS": 1,
        "RANCOUR": 1,
        "MALICE": 1,
        "RAGE": 1,
        "FURY": 1,
        "PROSECUTE": 1,
        "INTENDED": 1,
        "DESIGNS": 1,
        "AFFINITY": 1,
        "CONSANGUINITY": 1,
        "BYRON": 1,
        "SHELLEY": 1,
        "WALTER": 1,
        "SCOTT": 1,
        "MAURICE": 1,
        "DAUGHTER": 2,
        "IRISH": 1,
        "LANDOWNER": 1,
        "ROBERT": 1,
        "INCARNATION": 1,
        "VICES": 1,
        "IRELAND": 3,
        "COMES": 2,
        "PUBLIC": 2,
        "QUESTIONS": 2,
        "DECLARED": 2,
        "AUGUSTA": 1,
        "BRIEFLY": 1,
        "DISCONCERTED": 1,
        "CONTRADICTION": 1,
        "PRACTICAL": 1,
        "NECESSITY": 1,
        "HESITATE": 1,
        "MURPHY": 1,
        "HUNGER": 1,
        "DONKEY": 1,
        "OPPOSITION": 2,
        "DUALISTIC": 1,
        "PHILOSOPHY": 1,
        "TRIED": 3,
        "ESSAY": 1,
        "THOUGHTS": 1,
        "ABSOLUTELY": 1,
        "HOMOGENEOUS": 1,
        "FUNCTION": 1,
        "PRUDY": 1,
        "COOLLY": 1,
        "SAIL": 1,
        "ARRIVING": 1,
        "COCA": 1,
        "P": 1,
        "M": 1,
        "VILLAGE": 1,
        "AMAZON": 1,
        "BEAUTIFULLY": 1,
        "LOCATED": 1,
        "BANK": 1,
        "FIVE": 2,
        "ANCIENT": 1,
        "HEAVENS": 1,
        "THEE": 2,
        "FRESH": 1,
        "STRONG": 2,
        "HUMBLER": 1,
        "FUNCTIONS": 1,
        "AWFUL": 2,
        "CALL": 1,
        "COMMEND": 1,
        "UNTO": 1,
        "THY": 3,
        "GUIDANCE": 1,
        "HOUR": 2,
        "SIXTEENTH": 1,
        "CHAPTER": 3,
        "THAT'S": 3,
        "WANT": 3,
        "ADDRESSING": 1,
        "SMITH": 1,
        "ASHER'S": 1,
        "B": 1,
        "HENDERSON": 1,
        "ASHER": 1,
        "MOMENTS": 1,
        "MIRTH": 1,
        "INTERESTING": 1,
        "ASPECTS": 1,
        "WHOLLY": 1,
        "INERT": 1,
        "PHYSICALLY": 1,
        "ACTIVE": 1,
        "CORNERS": 1,
        "PHYSICAL": 1,
        "BODIES": 1,
        "OCCUPY": 1,
        "DAUGHTER'S": 1,
        "SPLENDID": 1,
        "DOWRY": 1,
        "PAY": 2,
        "CHARLES": 3,
        "MILLION": 1,
        "POUNDS": 1,
        "GOLD": 1,
        "CEDE": 1,
        "ENGLAND": 2,
        "VALUABLE": 1,
        "PORTS": 1,
        "MATCH": 2,
        "SIXTEEN": 2,
        "FIFTY": 3,
        "NINE": 1,
        "ARRANGED": 1,
        "LOSING": 1,
        "STEP": 2,
        "POWERFUL": 2,
        "FLEXIBLY": 1,
        "CONCENTRATED": 1,
        "COMMANDER": 1,
        "POSSIBLE": 5,
        "HOLDS": 1,
        "SYLLABLE": 1,
        "SOCIAL": 2,
        "UTILITY": 1,
        "INDETERMINATE": 1,
        "SENTENCE": 1,
        "RECOGNIZED": 1,
        "CRIMINOLOGISTS": 1,
        "TALK": 2,
        "SHEPHERD": 1,
        "CAREFULLY": 2,
        "CARAVAN": 1,
        "ROSALIE": 1,
        "WATCHING": 2,
        "PICKING": 1,
        "SHOWS": 1,
        "PIPES": 1,
        "SINGING": 1,
        "TREE": 1,
        "NATIVE": 1,
        "SIRE": 1,
        "ANSWERED": 3,
        "BASIN": 1,
        "UNFREQUENTLY": 1,
        "AGE": 1,
        "NATION": 1,
        "SEVERE": 2,
        "QUALITY": 1,
        "CRUELLY": 1,
        "TESTED": 1,
        "FAIL": 1,
        "OBLIGATION": 1,
        "SUPPORT": 1,
        "STATE": 3,
        "FEDERAL": 2,
        "CONSTITUTION": 1,
        "DUE": 2,
        "ALIKE": 1,
        "DERIVED": 1,
        "DEPENDENT": 1,
        "ALLEGIANCE": 1,
        "SOVEREIGN": 1,
        "STILLNESS": 1,
        "HUGE": 1,
        "INSTRUMENT": 1,
        "ITSELF": 4,
        "NOTES": 1,
        "STRUCK": 2,
        "INFINITE": 1,
        "DELICACY": 1,
        "DIFFERENCE": 1,
        "TOUCH": 1,
        "ENCOURAGEMENT": 1,
        "CONTINUES": 1,
        "SHOULDN'T": 2,
        "ANYBODY": 1,
        "IT'S": 2,
        "CAUGHT": 1,
        "LITERALLY": 1,
        "WILDERNESS": 1,
        "HUNTERS": 1,
        "CAMP": 1,
        "MUKOKI": 1,
        "PREDICTED": 1,
        "COLD": 4,
        "CLOUDLESS": 1,
        "INDIANS": 1,
        "PARLIAMENTS": 1,
        "DISSOLVE": 1,
        "FIXTURE": 1,
        "DUTY": 2,
        "FAIRLY": 1,
        "DONE": 4,
        "COMPLETED": 1,
        "FORTIETH": 1,
        "YEAR": 2,
        "SERVICE": 1,
        "OSTENSIBLE": 1,
        "REFORMATION": 1,
        "LATELY": 2,
        "FOURTH": 1,
        "CENTENARY": 1,
        "PURGE": 1,
        "CHURCH": 1,
        "IMBECILITIES": 1,
        "ACCOMPLISHED": 1,
        "UNITED": 2,
        "NAVY": 1,
        "RICHARDSON": 1,
        "COLLECTOR": 1,
        "SUBSCRIBED": 1,
        "RESULT": 2,
        "APPEALS": 1,
        "POSSESSED": 2,
        "NECESSARY": 1,
        "QUALIFICATIONS": 1,
        "NIGHTINGALE": 1,
        "ACCEPT": 1,
        "PERFORMING": 1,
        "TASKS": 1,
        "AHEAD": 1,
        "ANITA'S": 1,
        "CORRIDOR": 1,
        "WASN'T": 1,
        "SEALED": 1,
        "INTRUDER": 1,
        "ASLEEP": 1,
        "SLEW": 1,
        "THEREBY": 1,
        "FILLED": 3,
        "INSOMUCH": 1,
        "THREW": 1,
        "ENTIRE": 1,
        "ARMOR": 1,
        "FLED": 1,
        "GREATEST": 1,
        "EVENT": 1,
        "ACCELERATE": 1,
        "OPERATION": 1,
        "CONDUCTED": 1,
        "RAPIDITY": 1,
        "SEAT": 1,
        "VACANT": 1,
        "NOTWITHSTANDING": 1,
        "PRECAUTIONS": 1,
        "BISHOP": 1,
        "ALONE": 3,
        "WRETCHED": 2,
        "MAGNIFICENT": 1,
        "RADIANCE": 1,
        "JEAN": 1,
        "VALJEAN": 1,
        "WEPT": 3,
        "DINSMORE": 1,
        "EFFORT": 2,
        "WEARY": 1,
        "SAD": 2,
        "GREATLY": 1,
        "FATIGUED": 1,
        "BECAME": 2,
        "HOODIE": 2,
        "FLEW": 2,
        "SISTERS": 1,
        "RETURNED": 5,
        "FOLLOWED": 2,
        "SOMETIMES": 2,
        "HILL": 2,
        "TOP": 1,
        "HASTEN": 1,
        "HOPING": 1,
        "CATCH": 1,
        "TRAVELER": 1,
        "COMPREHENDS": 2,
        "COGNIZED": 1,
        "DRIVE": 1,
        "WOLVES": 1,
        "FERKO": 1,
        "STRAIGHT": 3,
        "KING": 2,
        "SMILE": 1,
        "ARMS": 3,
        "ASSIST": 1,
        "DISMOUNT": 1,
        "TEASING": 1,
        "VANISHED": 2,
        "PLACED": 3,
        "SHOULDERS": 1,
        "GIANT": 1,
        "WALL": 1,
        "END": 3,
        "DISTANCE": 1,
        "INN": 1,
        "REMEMBERED": 1,
        "FAIR": 3,
        "RESPITE": 1,
        "ACHING": 1,
        "MUSCLES": 1,
        "CRAMPED": 1,
        "PERILOUS": 1,
        "DAMNATION": 1,
        "REQUIRE": 1,
        "ILL": 2,
        "USED": 2,
        "NEEDED": 1,
        "JANE'S": 1,
        "STEADY": 1,
        "MILDNESS": 1,
        "BEAR": 3,
        "ATTACKS": 1,
        "TOLERABLE": 1,
        "TRANQUILLITY": 1,
        "RESOLVE": 1,
        "HUNDRED": 2,
        "ALREADY": 1,
        "CLEARED": 1,
        "FUEL": 1,
        "CREW": 1,
        "BEGIN": 2,
        "EXCURSION": 1,
        "EVIDENT": 1,
        "PREVENTED": 1,
        "MOMENTARY": 1,
        "THINKING": 1,
        "POINTS": 2,
        "PERHAPS": 5,
        "HALF": 3,
        "RECLINING": 1,
        "VISION": 1,
        "RIVETED": 1,
        "PORTRAIT": 1,
        "LENGTH": 1,
        "HOURS": 1,
        "PURSUIT": 2,
        "BATTLE": 1,
        "EXCEPT": 3,
        "PERSONS": 1,
        "COMMENCED": 1,
        "MOUSE": 1,
        "CROSSING": 1,
        "CRICKET": 1,
        "SINGLE": 2,
        "CHIRP": 1,
        "COMFORT": 2,
        "SUPPOSITIONS": 1,
        "DEATH": 2,
        "DIFFICULT": 2,
        "CONCERNED": 1,
        "ERROR": 1,
        "RADIUS": 1,
        "VECTOR": 1,
        "ADAMS": 1,
        "PERFECT": 1,
        "EASE": 1,
        "DRIVEN": 1,
        "USUAL": 1,
        "FOREVER": 1,
        "BROKENHEARTED": 1,
        "UNCOMMONLY": 1,
        "BOLD": 2,
        "GUIDE": 1,
        "ANSWER": 1,
        "FAILS": 1,
        "ELDEST": 1,
        "BROTHER": 1,
        "CORN": 2,
        "BARNS": 1,
        "PRAYER": 2,
        "WEAKNESS": 1,
        "KIND": 2,
        "GUARDIAN": 1,
        "SPIRIT": 2,
        "LACK": 1,
        "SUBJECTS": 1,
        "STARTED": 1,
        "INCAPACITY": 1,
        "CONTRIBUTE": 1,
        "OBVIOUS": 2,
        "CONCEAL": 1,
        "DISAPPOINTMENT": 1,
        "INDEFINITE": 1,
        "ALTERATION": 1,
        "MONSTROUS": 1,
        "CROWDS": 1,
        "PACKED": 1,
        "MASSES": 1,
        "INDISTINGUISHABLE": 1,
        "CLAMOURING": 1,
        "HAILING": 1,
        "IMPRISONED": 1,
        "DEBATED": 1,
        "SHOUTING": 1,
        "THOUSANDS": 1,
        "BEYOND": 1,
        "DOORWAY": 1,
        "RESCUED": 1,
        "UTTERLY": 1,
        "UNJUST": 1,
        "NOTION": 1,
        "JUSTICE": 1,
        "PERFECTLY": 1,
        "SUM": 1,
        "WORD": 3,
        "WORST": 1,
        "FROG": 1,
        "I'D": 1,
        "POLLYANNA": 1,
        "SCHEME": 1,
        "YOURS": 1,
        "WHOLESALE": 1,
        "WEALTH": 1,
        "YOU'VE": 1,
        "PROBLEM": 1,
        "HEAVEN": 1,
        "BLESS": 1,
        "CARRIER": 1,
        "CHEERFUL": 1,
        "CONSTANCY": 1,
        "KEEP": 1,
        "UNHAPPY": 1,
        "SORRY": 1,
        "IMPLORED": 1,
        "HOUARN": 1,
        "BIRDS": 1,
        "CONTINUE": 1,
        "FLYING": 1,
        "REACH": 2,
        "HARDINESS": 1,
        "KNIGHT": 2,
        "ARMED": 1,
        "DRESSED": 1,
        "SHIELD": 1,
        "MOUNTED": 1,
        "HORSEBACK": 1,
        "SPEAR": 1,
        "PACE": 1,
        "SHIP": 2,
        "TREMBLED": 1,
        "HAIR": 1,
        "ROBES": 1,
        "SHONE": 1,
        "MEDEIA": 2,
        "HID": 1,
        "VEIL": 1,
        "FAWLEY": 1,
        "GETTING": 1,
        "ADVANCED": 1,
        "PLENTEOUS": 1,
        "FIRE": 2,
        "UNABLE": 1,
        "RETURNINGS": 1,
        "PLEASANT": 2,
        "DESIRABLE": 1,
        "PROFESSION": 1,
        "IMPOSING": 1,
        "EFFECT": 2,
        "ARGUMENT": 2,
        "WISHES": 1,
        "PROVED": 2,
        "UNANSWERABLE": 1,
        "SHOWN": 2,
        "CONDUCTOR": 2,
        "PORT": 1,
        "WHITHER": 1,
        "BOUND": 1,
        "BRISTOL": 2,
        "BROTHER'S": 1,
        "CORRESPONDENT": 1,
        "LIVED": 2,
        "LONDON": 2,
        "WEEKS": 1,
        "SAYING": 2,
        "YOUTHS": 1,
        "TABLE": 4,
        "FOUNTAIN": 1,
        "EAGLES": 1,
        "LINEN": 1,
        "BEATRICE": 1,
        "HESITATION": 1,
        "COUPLE": 1,
        "SUTTON": 1,
        "ANNA'S": 1,
        "REASSURINGLY": 1,
        "YEA": 1,
        "RACE": 2,
        "LOTH": 1,
        "SIT": 1,
        "BOLDLY": 1,
        "PEOPLE'S": 1,
        "SUBORNING": 1,
        "DIVERS": 1,
        "DRAW": 1,
        "POOR": 2,
        "WHALE": 1,
        "LYING": 1,
        "ACROSS": 1,
        "STRAIT": 1,
        "HORSES": 4,
        "TRAMPLED": 2,
        "RIBS": 1,
        "LONGER": 1,
        "VASSILI": 1,
        "PEG": 1,
        "BECOMING": 1,
        "REVERENCE": 1,
        "SQUEERS": 1,
        "MICAWBER": 2,
        "FREE": 4,
        "ACTIVELY": 1,
        "ENGAGED": 1,
        "PURSUITS": 1,
        "CULTIVATION": 1,
        "STOCK": 1,
        "LANGUAGE": 1,
        "HORROR": 1,
        "MEDITATING": 1,
        "SITUATION": 2,
        "RECALLING": 1,
        "FACES": 1,
        "RAPIDLY": 1,
        "FALLING": 1,
        "HARM": 1,
        "CONTRADICTS": 1,
        "SOUNDEST": 1,
        "CONCLUSIONS": 1,
        "CONCERNING": 1,
        "ADVANTAGE": 1,
        "PRESERVES": 1,
        "PRECIOUS": 1,
        "PERSONALITY": 1,
        "INDIVIDUALITY": 1,
        "GOAT": 2,
        "YOU'RE": 1,
        "PRAY": 1,
        "DECK": 1,
        "PRETTY": 1,
        "BRAKE": 1,
        "BELIEF": 1,
        "TRUSTED": 2,
        "UNFORTUNATELY": 1,
        "BANK'S": 1,
        "FINANCIAL": 1,
        "TRANSACTIONS": 1,
        "REFUNDED": 1,
        "NINETEEN": 1,
        "FEEBLE": 1,
        "FORT'S": 1,
        "WOMAN'S": 1,
        "BESIEGED": 1,
        "ART": 1,
        "FANE'S": 1,
        "FORGETFUL": 1,
        "MUSE": 1,
        "REDEEM": 1,
        "GENTLE": 1,
        "IDLY": 1,
        "SING": 2,
        "EAR": 1,
        "DOTH": 1,
        "LAYS": 1,
        "ESTEEM": 1,
        "GIVES": 1,
        "SKILL": 1,
        "ENTERTAINED": 1,
        "EVERYBODY": 2,
        "INTIMATE": 1,
        "LUGGAGE": 1,
        "HOTEL": 1,
        "STAY": 2,
        "WESTGATE": 1,
        "GENTEEL": 1,
        "TOPS": 1,
        "HEADS": 2,
        "WARTY": 1,
        "RED": 1,
        "SKIN": 1,
        "GREW": 1,
        "FEATHERS": 1,
        "HAIRS": 1,
        "CRANES": 1,
        "AWAKENED": 1,
        "DALE": 2,
        "AWARE": 2,
        "PRECAUTIONARY": 1,
        "MEASURE": 1,
        "DALE'S": 1,
        "ENFORCED": 1,
        "PRESENCE": 1,
        "PREVENT": 1,
        "THOROUGHLY": 1,
        "APPROVED": 1,
        "ARTHUR'S": 1,
        "GRACEFUL": 1,
        "MODE": 1,
        "PROPOSING": 1,
        "GRANDFATHER'S": 1,
        "HEALTH": 1,
        "FARMERS": 1,
        "HATED": 2,
        "POYSER": 1,
        "PLENTY": 1,
        "EAT": 1,
        "ICE": 1,
        "FOOD": 2,
        "HOUSES": 2,
        "HALL": 2,
        "O": 2,
        "FIELDFARE": 1,
        "HEAR": 1,
        "WHETHER": 4,
        "TIS": 1,
        "DWELLING": 1,
        "HOUSEHOLD": 1,
        "TEARS": 1,
        "PENITENTLY": 1,
        "SOBS": 1,
        "BREAKING": 1,
        "DESTROYED": 1,
        "EARTHQUAKE": 1,
        "SUMMED": 1,
        "ELEMENTAL": 1,
        "TROPICAL": 1,
        "LUXURIANT": 1,
        "WAZIR": 1,
        "WEAVING": 1,
        "HUSBAND'S": 1,
        "MAJOR": 1,
        "JAMES": 1,
        "H": 1,
        "GALES": 1,
        "OWNER": 1,
        "EIGHTEEN": 1,
        "WOMEN": 1,
        "SLAVES": 1,
        "TOIL": 1,
        "LESSON": 1,
        "ARIGHT": 1,
        "AH": 1,
        "FAVOURITE": 1,
        "PUPIL": 1,
        "TEACH": 1,
        "WILLING": 1,
        "LATE": 1,
        "QUIET": 2,
        "BUZZING": 1,
        "TOUCHES": 1,
        "FINISHED": 1,
        "CHARLOTTE": 1,
        "INNOCENCE": 1,
        "MANIFEST": 1,
        "CARLYLE": 1,
        "DEADLY": 1,
        "EXTREME": 1,
        "PERUSAL": 1,
        "LADYSHIP": 1,
        "REAPPEAR": 1,
        "GRAND": 1,
        "APPOINTED": 1,
        "HOSTESS": 1,
        "AUTHOR": 1,
        "LARGEST": 1,
        "DONATION": 1,
        "SCHOOL": 1,
        "UNUSUALLY": 1,
        "PASSED": 2,
        "COUNCIL": 1,
        "DELIBERATING": 1,
        "OCCURRENCE": 1,
        "GUESSED": 1,
        "IMAGINE": 1,
        "LEARNED": 1,
        "SECRET": 1,
        "FOURTEEN": 1,
        "MOUNT": 1,
        "OLYMPUS": 1,
        "GROANING": 1,
        "FEELING": 1,
        "INSULT": 1,
        "SELF": 1,
        "CONDEMNING": 1,
        "SATISFIED": 1,
        "LODGINGS": 1,
        "ROKESMITH": 1,
        "DEPARTED": 2,
        "ERRAND": 1,
        "ACCOMPANIED": 1,
        "BOFFIN": 1,
        "JOG": 1,
        "TROT": 1,
        "BELLA": 1,
        "VAGUE": 1,
        "TREPIDATION": 1,
        "CONSULTATION": 1,
        "SUMMIT": 1,
        "COUNTRY'S": 1,
        "HONORS": 1,
        "DESCEND": 1,
        "EXALTED": 1,
        "EMINENCE": 1,
        "REFLECTED": 1,
        "EXERTION": 1,
        "MERIT": 1,
        "SAVE": 1,
        "UNWELCOME": 1,
        "REVERSE": 1,
        "SNAKE": 2,
        "HISSING": 1,
        "WRIGGLING": 1,
        "CREEPING": 1,
        "ANTHEA'S": 1,
        "HISSES": 1,
        "AWAKE": 1,
        "CREEPS": 1,
        "WRIGGLY": 1,
        "CREEP": 1,
        "SWAM": 1,
        "SWIFTLY": 1,
        "LAND": 1,
        "NOTICED": 1,
        "GEPPETTO": 1,
        "SHIVERING": 2,
        "SHAKING": 1,
        "FEVER": 1,
        "BIRD": 1,
        "OTHERWISE": 1,
        "OBJECTIONS": 1,
        "CARRIAGE": 2,
        "SERVANT": 1,
        "SMART": 1,
        "STRICT": 1,
        "EXACTING": 1,
        "SESSIONS": 1,
        "PIRATICAL": 1,
        "CRUISING": 1,
        "AROUND": 2,
        "PRIZES": 1,
        "TAKING": 2,
        "VACATION": 1,
        "DEALING": 1,
        "DISTINCTION": 1,
        "BECOME": 1,
        "INVOLVED": 1,
        "HOPELESS": 1,
        "CONFUSIONS": 1,
        "HITHERTO": 2,
        "PROSPEROUS": 1,
        "APPLIES": 1,
        "CEREBRAL": 1,
        "CONCENTRATION": 1,
        "TYPES": 1,
        "FREQUENTLY": 1,
        "NATURALLY": 1,
        "WANDERS": 1,
        "CARES": 1,
        "TRUMP": 1,
        "CARD": 1,
        "COMMENCEMENT": 1,
        "HURRIED": 1,
        "STATIONS": 1,
        "COLONEL": 1,
        "WUGSBY'S": 1,
        "CHAIR": 1,
        "WAITED": 1,
        "PATIENTLY": 1,
        "SIX": 1,
        "MILLIONS": 1,
        "SELL": 1,
        "WHATEVER": 2,
        "PRICE": 1,
        "DUBLIN": 1,
        "PAIR": 1,
        "ALTERNATIVES": 1,
        "PILLOW": 1,
        "FALL": 1,
        "EMILY": 1,
        "ETERNAL": 1,
        "HILLS": 1,
        "GOD'S": 1,
        "UNBEGINNING": 1,
        "BANISHING": 1,
        "ASSAILED": 1,
        "REVELATION": 1,
        "SOLITUDE": 1,
        "ALIVE": 1,
        "EXPLANATION": 1,
        "HESITATING": 1,
        "INSTANCE": 1,
        "UNINVITED": 1,
        "PRECEDED": 1,
        "LOWER": 1,
        "TAR": 1,
        "JEDDAK": 1,
        "DICTATES": 1,
        "AGES": 2,
        "DRAGON": 2,
        "DIRECTLY": 1,
        "STABLE": 1,
        "LIGHTNING": 1,
        "SPEED": 1,
        "PRISONER": 1,
        "FLOWN": 1,
        "WARILY": 1,
        "CUNNING": 1,
        "GLOSS": 1,
        "CONCEALMENT": 1,
        "AUGHT": 1,
        "DAMSEL": 1,
        "IDEA": 1,
        "AROUSE": 1,
        "PARTICULAR": 1,
        "ENTHUSIASM": 1,
        "DIARY": 1,
        "CONCLUDE": 1,
        "SCATTERED": 1,
        "ASHES": 1,
        "TWIGS": 1,
        "CHASING": 1,
        "ENGRAVING": 1,
        "CARVING": 1,
        "STONES": 1,
        "STEEL": 1,
        "OTHERS": 1,
        "SURPASS": 1,
        "ALLEGING": 1,
        "CONFLICTS": 1,
        "HONEST": 1,
        "CAVALIER": 1,
        "MAINTAIN": 1,
        "WHIGS": 1,
        "ROUNDHEADS": 1,
        "UNDISTURBED": 1,
        "CONFLICT": 1,
        "EXTREMELY": 1,
        "PERPLEXED": 1,
        "PERMIT": 2,
        "FAIN": 1,
        "TROOPER": 1,
        "ADMIRINGLY": 1,
        "WEIGHED": 1,
        "MONTGOMERY": 1,
        "DIRECT": 1,
        "MIDST": 1,
        "HORSE": 1,
        "ANGRY": 1,
        "AMUSED": 1,
        "ELEVEN": 1,
        "CHANCES": 1,
        "STORM": 1,
        "HADDEN": 1,
        "GLANCED": 1,
        "RIFLE": 1,
        "LAID": 1,
        "STABILITY": 1,
        "SOCIETY": 1,
        "HOOFMARKED": 1,
        "PRESENTED": 1,
        "CONFUSED": 1,
        "TRACES": 1,
        "BESIDES": 1,
        "CRITICAL": 1,
        "CONDITION": 2,
        "ULTIMATE": 1,
        "SUCCESS": 1,
        "AMERICANS": 1,
        "IMMENSE": 1,
        "EFFORTS": 1,
        "UNATTENDED": 1,
        "RECOVERED": 1,
        "INNOCENT": 1,
        "ACCORDINGLY": 1,
        "SOLEMN": 1,
        "FERVID": 1,
        "POSITIVELY": 1,
        "DESCRIBED": 1,
        "REMOVE": 1,
        "CONVICTION": 1,
        "SAMPLE": 1,
        "ARTICLE": 1,
        "ASKING": 1,
        "DISTRICT": 1,
        "ATTORNEY": 1,
        "MISSED": 1,
        "SAMPLES": 1,
        "WERNER": 1,
        "MACKAY": 1,
        "EXPLAINED": 1,
        "DISCUSSION": 1,
        "ADOPTED": 1,
        "SERVANTS": 2,
        "COMMITTEE": 1,
        "UNANIMOUS": 1,
        "CIRCUMSTANCED": 1,
        "KEEN": 1,
        "BLUE": 1,
        "MINE": 1,
        "GRATEFULLY": 1,
        "VANISH": 1,
        "VIGOROUS": 1,
        "BITES": 1,
        "TALKED": 1,
        "CEREMONY": 1,
        "GENUINE": 1,
        "APPALLED": 1,
        "INDIGNATION": 1,
        "TWISTING": 1,
        "MOUSTACHES": 1,
        "DECLINE": 1,
        "DISCUSS": 1,
        "OBSERVED": 1,
        "GENTLY": 1,
        "SEEM": 1,
        "SHARE": 1,
        "DISLIKE": 1,
        "DEPARTMENTS": 1,
        "SEEING": 1,
        "SUBORDINATES": 1,
        "RECEIVING": 1,
        "VISITORS": 1,
        "HEAVY": 1,
        "MILD": 1,
        "REMONSTRANCE": 1,
        "ESCAPED": 1,
        "OBJECTION": 1,
        "MIKE": 1,
        "PSMITH": 1,
        "DRESSING": 1,
        "LEG": 1,
        "RUBBED": 1,
        "SMELT": 1,
        "WAVED": 1,
        "SINKING": 1,
        "PROFOUNDEST": 1,
        "SLUMBER": 1,
        "FRIGHTENED": 1,
        "DESPAIR": 1,
        "CREPT": 1,
        "NOVEL": 1,
        "DEFENCELESS": 1,
        "CONFRONTED": 1,
        "HUGO": 1,
        "IMAGINATION": 1,
        "MONOPOLIZED": 1,
        "TRACKLESS": 1,
        "WOODS": 1,
        "BLAZING": 1,
        "SPREADING": 1,
        "CLOAK": 1,
        "SANK": 1,
        "FELLOWS": 1,
        "TRISTRAM": 1,
        "MONTHS": 1,
        "BRAVE": 1,
        "GRATEFUL": 1,
        "GENEROUS": 1,
        "KINDNESS": 1,
        "SEPARATE": 2,
        "PERCEPTIONS": 1,
        "JUDGMENTS": 1,
        "COMPARE": 1,
        "ALLEGED": 1,
        "PERCEIVES": 1,
        "APART": 2,
        "CHAINED": 1,
        "DESTINIES": 1,
        "SERENE": 1,
        "NERVES": 1,
        "RENEWED": 1,
        "DUTIES": 1,
        "RETIREMENT": 1,
        "TIMED": 1,
        "FINISH": 1,
        "RECEPTION": 1
    },
    "duration_per_book_min": {
        "12": 0.049,
        "20": 0.225,
        "33": 0.261,
        "35": 0.223,
        "45": 0.044,
        "47": 0.264,
        "62": 0.254,
        "84": 0.378,
        "102": 0.237,
        "121": 0.507,
        "128": 0.253,
        "130": 0.222,
        "135": 0.244,
        "141": 0.235,
        "153": 0.081,
        "161": 0.227,
        "163": 0.25,
        "204": 0.216,
        "210": 0.199,
        "283": 0.178,
        "308": 0.275,
        "345": 0.358,
        "370": 0.215,
        "500": 0.391,
        "501": 0.035,
        "507": 0.518,
        "540": 0.194,
        "541": 0.115,
        "580": 0.211,
        "600": 0.271,
        "619": 0.26,
        "640": 0.769,
        "641": 0.466,
        "643": 0.76,
        "697": 0.255,
        "708": 0.256,
        "730": 0.237,
        "735": 0.067,
        "766": 0.247,
        "768": 0.261,
        "815": 0.267,
        "836": 0.272,
        "852": 0.491,
        "883": 0.238,
        "967": 0.375,
        "974": 0.05,
        "1041": 0.217,
        "1098": 0.035,
        "1153": 0.236,
        "1184": 1.133,
        "1202": 0.268,
        "1250": 0.235,
        "1251": 0.479,
        "1257": 0.855,
        "1259": 0.053,
        "1260": 0.206,
        "1273": 0.222,
        "1342": 0.642,
        "1353": 0.245,
        "1404": 0.962,
        "1438": 0.046,
        "1477": 0.485,
        "1497": 0.264,
        "1624": 0.256,
        "1627": 0.237,
        "1719": 0.221,
        "1734": 0.257,
        "1953": 0.049,
        "2021": 0.241,
        "2046": 0.238,
        "2147": 0.234,
        "2148": 0.251,
        "2158": 0.491,
        "2376": 0.445,
        "2435": 0.33,
        "2439": 0.229,
        "2488": 0.057,
        "2505": 0.226,
        "2524": 0.174,
        "2554": 0.068,
        "2591": 0.214,
        "2600": 0.255,
        "2612": 0.207,
        "2657": 0.232,
        "2681": 0.232,
        "2814": 0.189,
        "2842": 0.242,
        "2848": 0.238,
        "2865": 0.261,
        "2866": 0.213,
        "3005": 0.225,
        "3050": 0.202,
        "3178": 0.221,
        "3268": 0.035,
        "3282": 0.262,
        "3300": 0.251,
        "3322": 0.262,
        "3437": 0.235,
        "3440": 0.077,
        "3454": 0.948,
        "3533": 0.247,
        "3748": 0.256,
        "3800": 0.175,
        "4018": 0.198,
        "4229": 0.231,
        "4363": 0.404,
        "4367": 0.242,
        "4599": 0.247,
        "4693": 0.763,
        "4735": 0.246,
        "4925": 0.21,
        "5270": 0.208,
        "5308": 0.259,
        "5312": 0.261,
        "5664": 0.251,
        "5676": 0.238,
        "5803": 0.235,
        "5827": 0.453,
        "5961": 0.235,
        "6098": 0.424,
        "6100": 0.246,
        "6124": 0.135,
        "6308": 0.064,
        "6328": 1.089,
        "6424": 0.076,
        "6753": 0.256,
        "6754": 0.208,
        "6812": 0.249,
        "6884": 0.199,
        "6933": 0.182,
        "6955": 0.223,
        "7040": 0.055,
        "7091": 0.246,
        "7142": 0.155,
        "7345": 0.244,
        "7437": 0.237,
        "8166": 0.247,
        "8318": 0.034,
        "8813": 0.26,
        "8859": 0.259,
        "8933": 0.229,
        "9072": 0.209,
        "9296": 0.255,
        "9301": 0.22,
        "9662": 0.261,
        "9963": 0.654,
        "10337": 0.174,
        "10360": 0.447,
        "10378": 0.241,
        "10446": 0.257,
        "10615": 0.239,
        "10800": 0.234,
        "10991": 0.066,
        "11146": 0.179,
        "11417": 0.215,
        "12069": 0.198,
        "12081": 0.263,
        "12163": 0.264,
        "12170": 0.193,
        "12587": 0.589,
        "12758": 0.256,
        "13110": 0.172,
        "14021": 0.249,
        "14328": 0.132,
        "14916": 0.264,
        "15202": 0.087,
        "15263": 0.422,
        "15709": 0.264,
        "16134": 0.054,
        "16140": 0.238,
        "16537": 0.453,
        "16566": 0.262,
        "16567": 0.261,
        "17188": 0.206,
        "17498": 0.415,
        "17504": 0.253,
        "17611": 0.091,
        "18362": 1.163,
        "18640": 0.169,
        "18776": 0.221,
        "18857": 0.257,
        "18948": 0.486,
        "19066": 0.149,
        "19209": 0.226,
        "19211": 0.077,
        "19221": 0.241,
        "19403": 0.227,
        "19771": 0.083,
        "19831": 0.206,
        "19993": 0.243,
        "20064": 0.272,
        "20183": 0.176,
        "20795": 0.114,
        "21004": 0.258,
        "21301": 0.064,
        "21873": 0.221,
        "21892": 0.231,
        "22215": 0.243,
        "22759": 0.362,
        "24160": 0.237,
        "24711": 0.053,
        "24811": 0.046,
        "25326": 0.231,
        "25652": 0.26,
        "25953": 0.236,
        "26117": 0.252,
        "26640": 0.248,
        "26732": 0.127,
        "27683": 0.205,
        "27826": 0.246,
        "28054": 0.268,
        "28613": 0.351,
        "30601": 0.238,
        "30754": 0.253,
        "32429": 0.148,
        "32547": 0.444,
        "33800": 0.035,
        "34912": 0.202,
        "35002": 0.21,
        "35505": 0.247,
        "35679": 0.229,
        "35793": 0.208,
        "38172": 0.221,
        "38556": 0.269,
        "38693": 0.229,
        "39324": 0.482,
        "39592": 0.259,
        "39843": 0.221,
        "40077": 0.113,
        "41020": 0.142,
        "43538": 0.095
    },
    "book distribution": {
        "26732": 1,
        "17498": 2,
        "35793": 1,
        "16537": 2,
        "62": 2,
        "6328": 5,
        "6933": 1,
        "12587": 3,
        "2865": 1,
        "2376": 2,
        "2814": 1,
        "3005": 1,
        "735": 1,
        "18362": 5,
        "161": 1,
        "15263": 2,
        "2612": 1,
        "121": 2,
        "697": 1,
        "7142": 1,
        "12081": 1,
        "7091": 1,
        "1184": 6,
        "10378": 1,
        "1477": 2,
        "16566": 1,
        "19771": 1,
        "30754": 1,
        "2158": 2,
        "3178": 1,
        "28054": 1,
        "1250": 1,
        "3800": 1,
        "4693": 3,
        "1719": 1,
        "1342": 3,
        "9963": 3,
        "3282": 1,
        "2866": 1,
        "3440": 2,
        "24160": 1,
        "2488": 1,
        "17611": 1,
        "19211": 1,
        "7040": 1,
        "5827": 2,
        "41020": 1,
        "21004": 1,
        "16134": 1,
        "1353": 1,
        "4363": 2,
        "8318": 1,
        "5676": 1,
        "39592": 1,
        "6098": 2,
        "39843": 1,
        "3454": 4,
        "507": 2,
        "6424": 1,
        "2591": 1,
        "1734": 1,
        "283": 1,
        "9072": 1,
        "10360": 2,
        "9662": 1,
        "852": 2,
        "14916": 1,
        "18776": 1,
        "22759": 2,
        "345": 2,
        "2524": 1,
        "540": 1,
        "34912": 1,
        "1257": 4,
        "3748": 1,
        "26640": 1,
        "6124": 1,
        "40077": 1,
        "13110": 1,
        "20": 1,
        "12758": 2,
        "26117": 1,
        "43538": 1,
        "12069": 1,
        "2435": 2,
        "204": 1,
        "163": 1,
        "2681": 1,
        "2657": 1,
        "730": 1,
        "10615": 1,
        "1404": 4,
        "3300": 1,
        "24811": 1,
        "19403": 1,
        "4925": 1,
        "6812": 1,
        "10991": 1,
        "1624": 1,
        "39324": 2,
        "15709": 1,
        "27826": 1,
        "5664": 1,
        "9296": 1,
        "35679": 1,
        "8933": 1,
        "643": 3,
        "7345": 1,
        "9301": 1,
        "47": 1,
        "3533": 1,
        "21873": 1,
        "8813": 1,
        "5803": 1,
        "1259": 1,
        "38172": 1,
        "45": 1,
        "33": 1,
        "38693": 1,
        "18857": 1,
        "3437": 2,
        "5961": 1,
        "141": 1,
        "4735": 2,
        "1273": 1,
        "38556": 1,
        "35": 1,
        "5312": 1,
        "10800": 1,
        "33800": 1,
        "500": 2,
        "32547": 2,
        "24711": 1,
        "19209": 1,
        "19221": 1,
        "501": 1,
        "6955": 1,
        "2600": 1,
        "130": 1,
        "7437": 1,
        "128": 1,
        "20183": 1,
        "19831": 1,
        "2554": 1,
        "14021": 1,
        "308": 1,
        "12170": 1,
        "20064": 1,
        "18948": 2,
        "11146": 1,
        "25652": 1,
        "19066": 1,
        "2848": 1,
        "815": 1,
        "135": 1,
        "1438": 1,
        "14328": 1,
        "640": 3,
        "17504": 1,
        "6308": 1,
        "2147": 1,
        "4367": 1,
        "2148": 1,
        "28613": 2,
        "102": 1,
        "16140": 1,
        "768": 1,
        "12163": 1,
        "1497": 1,
        "15202": 1,
        "6100": 1,
        "20795": 1,
        "1251": 2,
        "153": 1,
        "1260": 1,
        "370": 1,
        "35505": 1,
        "8166": 1,
        "641": 2,
        "967": 2,
        "766": 1,
        "22215": 1,
        "600": 1,
        "19993": 1,
        "5308": 1,
        "1041": 1,
        "210": 1,
        "35002": 1,
        "4599": 1,
        "6754": 1,
        "25953": 1,
        "10337": 1,
        "1202": 1,
        "974": 1,
        "2505": 1,
        "3322": 1,
        "619": 1,
        "883": 1,
        "836": 1,
        "1953": 1,
        "17188": 1,
        "30601": 1,
        "580": 1,
        "18640": 1,
        "3268": 1,
        "21892": 1,
        "12": 1,
        "1627": 1,
        "1153": 1,
        "11417": 1,
        "4229": 1,
        "4018": 1,
        "25326": 1,
        "2439": 1,
        "3050": 1,
        "10446": 1,
        "21301": 1,
        "2842": 1,
        "32429": 1,
        "8859": 1,
        "84": 2,
        "1098": 1,
        "5270": 1,
        "2046": 1,
        "2021": 1,
        "6753": 1,
        "708": 1,
        "27683": 1,
        "16567": 1,
        "541": 1,
        "6884": 1
    },
    "chapter distribution": {
        "178103": 1,
        "87276": 2,
        "66016": 1,
        "116805": 1,
        "123507": 1,
        "281197": 1,
        "15081": 1,
        "34652": 1,
        "133395": 1,
        "169288": 1,
        "135987": 1,
        "93270": 1,
        "150679": 1,
        "130532": 1,
        "129974": 1,
        "115881": 1,
        "138486": 1,
        "199": 1,
        "126112": 1,
        "126959": 1,
        "56405": 1,
        "127691": 1,
        "121130": 1,
        "7763": 1,
        "2327": 2,
        "17499": 1,
        "73705": 1,
        "86710": 1,
        "74179": 1,
        "13056": 1,
        "29090": 1,
        "699": 1,
        "132705": 1,
        "24731": 1,
        "11963": 2,
        "140067": 1,
        "124147": 1,
        "64956": 1,
        "86041": 1,
        "93348": 1,
        "75791": 1,
        "121090": 1,
        "89940": 1,
        "36616": 1,
        "245687": 1,
        "88007": 1,
        "13006": 1,
        "3536": 1,
        "142752": 1,
        "268295": 1,
        "130517": 1,
        "31091": 1,
        "301693": 1,
        "28247": 1,
        "122947": 2,
        "124992": 1,
        "6181": 1,
        "292563": 1,
        "130531": 1,
        "276939": 2,
        "99122": 1,
        "132850": 2,
        "142363": 2,
        "60544": 1,
        "126302": 1,
        "76048": 1,
        "183988": 1,
        "7793": 1,
        "159228": 1,
        "135659": 1,
        "39971": 2,
        "64719": 1,
        "59268": 1,
        "175346": 1,
        "124445": 1,
        "74918": 1,
        "163607": 1,
        "56787": 1,
        "122443": 3,
        "123290": 1,
        "121069": 1,
        "185518": 1,
        "140718": 1,
        "258960": 1,
        "68770": 1,
        "129443": 1,
        "9206": 1,
        "28396": 1,
        "293973": 1,
        "27593": 1,
        "8675": 1,
        "126975": 1,
        "160602": 1,
        "75939": 1,
        "124368": 1,
        "129317": 1,
        "290365": 1,
        "131044": 1,
        "7371": 1,
        "33409": 1,
        "145083": 1,
        "122425": 1,
        "131113": 1,
        "102240": 1,
        "14936": 1,
        "294700": 1,
        "93314": 2,
        "281202": 1,
        "16632": 1,
        "80699": 1,
        "135884": 1,
        "156061": 1,
        "62850": 1,
        "163518": 1,
        "29012": 3,
        "28461": 1,
        "121742": 1,
        "122825": 1,
        "172357": 1,
        "141240": 1,
        "140639": 1,
        "124146": 1,
        "100429": 1,
        "121397": 1,
        "291107": 1,
        "122859": 1,
        "75807": 1,
        "130993": 1,
        "135777": 1,
        "292604": 1,
        "61958": 1,
        "281208": 1,
        "131004": 1,
        "15556": 2,
        "120325": 1,
        "281187": 2,
        "126539": 1,
        "7943": 1,
        "88761": 1,
        "86965": 1,
        "133442": 1,
        "121658": 1,
        "132821": 1,
        "47541": 1,
        "11977": 1,
        "130529": 1,
        "63496": 1,
        "125883": 2,
        "128684": 2,
        "97084": 1,
        "64588": 1,
        "291968": 1,
        "126864": 1,
        "55856": 1,
        "137004": 1,
        "137154": 1,
        "86814": 1,
        "88089": 1,
        "10702": 1,
        "104717": 1,
        "102372": 1,
        "132496": 1,
        "43303": 1,
        "130638": 1,
        "66622": 1,
        "63839": 1,
        "168500": 2,
        "156738": 1,
        "92935": 1,
        "2481": 1,
        "26485": 1,
        "133273": 1,
        "134787": 1,
        "64974": 2,
        "10172": 1,
        "121911": 1,
        "145706": 2,
        "7944": 1,
        "34667": 1,
        "108066": 1,
        "9052": 1,
        "1133": 1,
        "175359": 1,
        "65787": 1,
        "23924": 1,
        "7601": 1,
        "19373": 1,
        "139404": 1,
        "9210": 1,
        "281329": 1,
        "135063": 1,
        "139310": 1,
        "170976": 1,
        "280361": 1,
        "141613": 1,
        "139741": 1,
        "132847": 1,
        "137588": 1,
        "116804": 1,
        "126208": 1,
        "122647": 1,
        "219": 1,
        "129766": 1,
        "145700": 1,
        "11243": 1,
        "12312": 1,
        "101258": 1,
        "134419": 1,
        "144503": 1,
        "27670": 1,
        "123715": 1,
        "160952": 1,
        "133471": 1,
        "139272": 1,
        "122789": 1,
        "286667": 1,
        "48852": 1,
        "21625": 1,
        "302111": 1,
        "39477": 1,
        "7258": 1,
        "126738": 1,
        "118101": 1,
        "124439": 1,
        "50150": 1,
        "5331": 1,
        "123501": 1,
        "169291": 1,
        "127215": 1,
        "125140": 1,
        "131045": 1,
        "157243": 1,
        "66470": 1,
        "8663": 1,
        "128985": 1,
        "142744": 1,
        "19361": 1,
        "52164": 1,
        "135624": 1,
        "121079": 1,
        "174923": 1,
        "132537": 1,
        "12085": 1,
        "127369": 1,
        "275164": 1,
        "157768": 1,
        "101262": 1,
        "49755": 1,
        "152918": 1,
        "139612": 1,
        "10094": 1,
        "132610": 1,
        "130551": 1,
        "25947": 1,
        "298545": 1,
        "34599": 1,
        "143255": 1,
        "53035": 1,
        "26680": 1,
        "12915": 1,
        "366": 1,
        "178459": 1,
        "134420": 1,
        "155521": 1,
        "4136": 1,
        "159227": 1,
        "6397": 1,
        "124221": 1,
        "183930": 1,
        "179183": 1,
        "358": 1,
        "137628": 1,
        "287863": 1,
        "131276": 1,
        "302000": 1
    },
    "duration_per_chapter_min": {
        "199": 0.247,
        "219": 0.261,
        "358": 0.153,
        "366": 0.225,
        "699": 0.268,
        "1133": 0.238,
        "2327": 0.485,
        "2481": 0.149,
        "3536": 0.055,
        "4136": 0.238,
        "5331": 0.262,
        "6181": 0.238,
        "6397": 0.241,
        "7258": 0.268,
        "7371": 0.251,
        "7601": 0.251,
        "7763": 0.241,
        "7793": 0.209,
        "7943": 0.054,
        "7944": 0.192,
        "8663": 0.262,
        "8675": 0.068,
        "9052": 0.064,
        "9206": 0.159,
        "9210": 0.097,
        "10094": 0.231,
        "10172": 0.046,
        "10702": 0.253,
        "11243": 0.247,
        "11963": 0.508,
        "11977": 0.255,
        "12085": 0.231,
        "12312": 0.247,
        "12915": 0.259,
        "13006": 0.236,
        "13056": 0.255,
        "14936": 0.066,
        "15081": 0.182,
        "15556": 0.235,
        "16632": 0.264,
        "17499": 0.262,
        "19361": 0.209,
        "19373": 0.142,
        "21625": 0.208,
        "23924": 0.242,
        "24731": 0.175,
        "25947": 0.202,
        "26485": 0.238,
        "26680": 0.148,
        "27593": 0.198,
        "27670": 0.243,
        "28247": 0.245,
        "28396": 0.252,
        "28461": 0.244,
        "29012": 0.76,
        "29090": 0.221,
        "31091": 0.258,
        "33409": 0.046,
        "34599": 0.075,
        "34652": 0.265,
        "34667": 0.248,
        "36616": 0.057,
        "39477": 0.174,
        "39971": 0.491,
        "43303": 0.249,
        "47541": 0.234,
        "48852": 0.247,
        "49755": 0.215,
        "50150": 0.226,
        "52164": 0.238,
        "53035": 0.242,
        "55856": 0.223,
        "56405": 0.263,
        "56787": 0.202,
        "59268": 0.221,
        "60544": 0.076,
        "61958": 0.257,
        "62850": 0.229,
        "63496": 0.035,
        "63839": 0.272,
        "64588": 0.226,
        "64719": 0.264,
        "64956": 0.196,
        "64974": 0.458,
        "65787": 0.234,
        "66016": 0.208,
        "66470": 0.049,
        "66622": 0.193,
        "68770": 0.172,
        "73705": 0.083,
        "74179": 0.253,
        "74918": 0.174,
        "75791": 0.032,
        "75807": 0.045,
        "75939": 0.232,
        "76048": 0.257,
        "80699": 0.246,
        "86041": 0.262,
        "86710": 0.213,
        "86814": 0.092,
        "86965": 0.269,
        "87276": 0.415,
        "88007": 0.077,
        "88089": 0.237,
        "88761": 0.222,
        "89940": 0.237,
        "92935": 0.26,
        "93270": 0.225,
        "93314": 0.482,
        "93348": 0.213,
        "97084": 0.053,
        "99122": 0.221,
        "100429": 0.235,
        "101258": 0.253,
        "101262": 0.213,
        "102240": 0.249,
        "102372": 0.206,
        "104717": 0.176,
        "108066": 0.253,
        "115881": 0.241,
        "116804": 0.237,
        "116805": 0.216,
        "118101": 0.181,
        "120325": 0.235,
        "121069": 0.255,
        "121079": 0.145,
        "121090": 0.269,
        "121130": 0.158,
        "121397": 0.053,
        "121658": 0.261,
        "121742": 0.22,
        "121911": 0.132,
        "122425": 0.206,
        "122443": 0.649,
        "122647": 0.206,
        "122789": 0.199,
        "122825": 0.264,
        "122859": 0.044,
        "122947": 0.404,
        "123290": 0.256,
        "123501": 0.053,
        "123507": 0.201,
        "123715": 0.271,
        "124146": 0.207,
        "124147": 0.197,
        "124221": 0.256,
        "124368": 0.232,
        "124439": 0.185,
        "124445": 0.173,
        "124992": 0.034,
        "125140": 0.238,
        "125883": 0.391,
        "126112": 0.255,
        "126208": 0.081,
        "126302": 0.214,
        "126539": 0.235,
        "126738": 0.05,
        "126864": 0.035,
        "126959": 0.155,
        "126975": 0.216,
        "127215": 0.26,
        "127369": 0.049,
        "127691": 0.246,
        "128684": 0.444,
        "128985": 0.206,
        "129317": 0.237,
        "129443": 0.225,
        "129766": 0.215,
        "129974": 0.227,
        "130517": 0.265,
        "130529": 0.229,
        "130531": 0.265,
        "130532": 0.228,
        "130551": 0.176,
        "130638": 0.275,
        "130993": 0.209,
        "131004": 0.241,
        "131044": 0.257,
        "131045": 0.256,
        "131113": 0.21,
        "131276": 0.115,
        "132496": 0.068,
        "132537": 0.035,
        "132610": 0.229,
        "132705": 0.235,
        "132821": 0.229,
        "132847": 0.237,
        "132850": 0.481,
        "133273": 0.267,
        "133395": 0.261,
        "133442": 0.223,
        "133471": 0.259,
        "134419": 0.117,
        "134420": 0.258,
        "134787": 0.244,
        "135063": 0.261,
        "135624": 0.211,
        "135659": 0.261,
        "135777": 0.261,
        "135884": 0.251,
        "135987": 0.189,
        "137004": 0.255,
        "137154": 0.222,
        "137588": 0.258,
        "137628": 0.222,
        "138486": 0.207,
        "139272": 0.217,
        "139310": 0.264,
        "139404": 0.237,
        "139612": 0.198,
        "139741": 0.114,
        "140067": 0.221,
        "140639": 0.26,
        "140718": 0.135,
        "141240": 0.221,
        "141613": 0.246,
        "142363": 0.518,
        "142744": 0.208,
        "142752": 0.245,
        "143255": 0.064,
        "144503": 0.247,
        "145083": 0.227,
        "145700": 0.23,
        "145706": 0.539,
        "150679": 0.067,
        "152918": 0.231,
        "155521": 0.208,
        "156061": 0.255,
        "156738": 0.179,
        "157243": 0.272,
        "157768": 0.236,
        "159227": 0.261,
        "159228": 0.186,
        "160602": 0.25,
        "160952": 0.243,
        "163518": 0.229,
        "163607": 0.194,
        "168500": 0.486,
        "169288": 0.236,
        "169291": 0.21,
        "170976": 0.264,
        "172357": 0.247,
        "174923": 0.169,
        "175346": 0.099,
        "175359": 0.263,
        "178103": 0.127,
        "178459": 0.035,
        "179183": 0.205,
        "183930": 0.256,
        "183988": 0.178,
        "185518": 0.248,
        "245687": 0.091,
        "258960": 0.113,
        "268295": 0.142,
        "275164": 0.237,
        "276939": 0.424,
        "280361": 0.087,
        "281187": 0.494,
        "281197": 0.103,
        "281202": 0.225,
        "281208": 0.266,
        "281329": 0.238,
        "286667": 0.21,
        "287863": 0.261,
        "290365": 0.239,
        "291107": 0.221,
        "291968": 0.241,
        "292563": 0.259,
        "292604": 0.229,
        "293973": 0.095,
        "294700": 0.256,
        "298545": 0.257,
        "301693": 0.054,
        "302000": 0.199,
        "302111": 0.236
    }
}