{
    "speaker id frequency": {
        "38": 13,
        "78": 13,
        "118": 15,
        "127": 22,
        "152": 13,
        "154": 13,
        "201": 14,
        "204": 13,
        "252": 14,
        "253": 13,
        "255": 13,
        "335": 14,
        "345": 12,
        "359": 12,
        "365": 12,
        "405": 13,
        "481": 14,
        "512": 12,
        "548": 13,
        "559": 12,
        "594": 13,
        "639": 12,
        "778": 13,
        "781": 12
    },
    "duration_per_speaker_min": {
        "38": 2.56,
        "78": 2.615,
        "118": 2.41,
        "127": 2.291,
        "152": 3.151,
        "154": 2.87,
        "201": 2.139,
        "204": 2.719,
        "252": 2.911,
        "253": 2.584,
        "255": 2.244,
        "335": 2.929,
        "345": 2.856,
        "359": 2.428,
        "365": 2.398,
        "405": 2.642,
        "481": 2.761,
        "512": 2.843,
        "548": 2.58,
        "559": 2.834,
        "594": 2.73,
        "639": 2.604,
        "778": 2.417,
        "781": 2.741
    },
    "tokens": {
        "THE": 630,
        "DAY": 7,
        "PASSED": 4,
        "AWAY": 15,
        "IN": 170,
        "UTTER": 1,
        "SILENCE": 3,
        "NIGHT": 7,
        "CAME": 16,
        "WITHOUT": 10,
        "RECURRENCE": 1,
        "OF": 297,
        "NOISE": 2,
        "IT": 107,
        "IS": 75,
        "A": 206,
        "PRISONER": 4,
        "SAID": 34,
        "EDMOND": 3,
        "JOYFULLY": 1,
        "PERFECT": 3,
        "DID": 19,
        "NOT": 56,
        "CLOSE": 8,
        "HIS": 88,
        "EYES": 6,
        "YOU": 91,
        "DESTROY": 1,
        "EVERYTHING": 3,
        "FIRST": 11,
        "BREAK": 3,
        "YOUR": 33,
        "JUG": 2,
        "THEN": 23,
        "MAKE": 12,
        "ME": 45,
        "PLATE": 1,
        "IF": 28,
        "ALL": 59,
        "PRISONERS": 2,
        "FOLLOWED": 2,
        "EXAMPLE": 1,
        "GOVERNMENT": 1,
        "WOULD": 27,
        "BE": 48,
        "RUINED": 1,
        "I": 189,
        "SHALL": 11,
        "LEAVE": 2,
        "SAUCEPAN": 3,
        "AND": 369,
        "POUR": 1,
        "SOUP": 3,
        "INTO": 20,
        "THAT": 128,
        "SO": 47,
        "FOR": 83,
        "FUTURE": 2,
        "HOPE": 3,
        "WILL": 25,
        "DESTRUCTIVE": 1,
        "HAD": 72,
        "DISCOVERED": 2,
        "DANGER": 3,
        "SUBSTITUTED": 1,
        "LEVER": 1,
        "CHISEL": 1,
        "ENCOURAGED": 1,
        "BY": 66,
        "THIS": 38,
        "DISCOVERY": 2,
        "DETERMINED": 1,
        "TO": 243,
        "ASSIST": 1,
        "INDEFATIGABLE": 1,
        "LABORER": 1,
        "RESTORING": 1,
        "VIGOR": 1,
        "AGILITY": 1,
        "LIMBS": 1,
        "EXERCISE": 2,
        "PREPARING": 1,
        "HIMSELF": 13,
        "DESTINY": 1,
        "AT": 49,
        "INTERVALS": 1,
        "HE": 136,
        "LISTENED": 1,
        "LEARN": 3,
        "BEGUN": 3,
        "AGAIN": 9,
        "GREW": 2,
        "IMPATIENT": 1,
        "PRUDENCE": 1,
        "REPROACHED": 2,
        "WITH": 95,
        "HAVING": 8,
        "THUS": 4,
        "EMPLOYED": 1,
        "HOURS": 5,
        "VAIN": 1,
        "HOPES": 1,
        "PRAYER": 1,
        "DESPONDENCY": 1,
        "DURING": 3,
        "SIX": 5,
        "YEARS": 4,
        "BEEN": 21,
        "IMPRISONED": 1,
        "WHAT": 32,
        "MIGHT": 6,
        "HAVE": 48,
        "ACCOMPLISHED": 3,
        "TOOK": 9,
        "WALL": 6,
        "ARE": 35,
        "MINING": 1,
        "OUTER": 2,
        "FORTRESS": 1,
        "BUT": 58,
        "SEA": 9,
        "HOPED": 1,
        "SUPPOSING": 1,
        "SUCCEEDED": 2,
        "SHOULD": 12,
        "THROWN": 1,
        "MYSELF": 6,
        "WELL": 16,
        "RETURNED": 5,
        "VOICE": 5,
        "MORROW": 2,
        "JAILER": 3,
        "ALWAYS": 12,
        "BROUGHT": 8,
        "DANTES": 2,
        "AN": 43,
        "IRON": 2,
        "CONTAINED": 1,
        "BOTH": 5,
        "WAS": 118,
        "ONE": 38,
        "THESE": 12,
        "UNCOVERED": 1,
        "WHICH": 29,
        "MUST": 13,
        "REMOVE": 1,
        "FROM": 44,
        "ITS": 16,
        "SOCKET": 1,
        "STROVE": 1,
        "DO": 16,
        "NAILS": 1,
        "THEY": 45,
        "WERE": 38,
        "TOO": 9,
        "WEAK": 1,
        "FRAGMENTS": 2,
        "BROKE": 2,
        "AFTER": 23,
        "HOUR": 2,
        "USELESS": 1,
        "TOIL": 1,
        "PAUSED": 2,
        "SOON": 13,
        "FURY": 1,
        "WAVES": 3,
        "SIGHT": 2,
        "SHARP": 4,
        "ROCKS": 3,
        "ANNOUNCED": 2,
        "APPROACH": 2,
        "DEATH": 6,
        "TERRIFIED": 1,
        "USED": 3,
        "MY": 67,
        "SKILL": 1,
        "INTELLIGENCE": 1,
        "AS": 94,
        "MAN": 19,
        "SAILOR": 1,
        "STRUGGLE": 1,
        "AGAINST": 3,
        "WRATH": 1,
        "GOD": 2,
        "BECAUSE": 4,
        "HAPPY": 3,
        "FRENCHMAN": 1,
        "NAME": 6,
        "WHEN": 38,
        "MORNING": 3,
        "EVENING": 3,
        "MEALS": 1,
        "THOUGHT": 13,
        "CAST": 2,
        "THEM": 33,
        "OUT": 34,
        "WINDOW": 4,
        "THINK": 11,
        "EATEN": 1,
        "KEPT": 2,
        "WORD": 1,
        "TWICE": 2,
        "THROUGH": 6,
        "BARRED": 2,
        "APERTURE": 1,
        "PROVISIONS": 1,
        "HIM": 41,
        "JUST": 9,
        "REMOVED": 3,
        "BED": 3,
        "HEARD": 7,
        "THREE": 4,
        "KNOCKS": 1,
        "THREW": 4,
        "ON": 51,
        "KNEES": 2,
        "AM": 12,
        "HERE": 7,
        "GONE": 4,
        "VANISH": 3,
        "COULD": 26,
        "COURSES": 1,
        "RIVERS": 1,
        "DAEMON": 2,
        "GENERALLY": 1,
        "AVOIDED": 1,
        "POPULATION": 1,
        "COUNTRY": 5,
        "CHIEFLY": 3,
        "COLLECTED": 1,
        "MIGHTY": 2,
        "SHOCK": 1,
        "EARTHQUAKE": 1,
        "SPLIT": 1,
        "CRACKED": 1,
        "TREMENDOUS": 2,
        "OVERWHELMING": 1,
        "SOUND": 3,
        "WORK": 6,
        "FINISHED": 1,
        "FEW": 6,
        "MINUTES": 3,
        "TUMULTUOUS": 1,
        "ROLLED": 1,
        "BETWEEN": 2,
        "ENEMY": 5,
        "KNOW": 16,
        "FRIENDS": 5,
        "SNATCHED": 1,
        "LEFT": 10,
        "DESOLATE": 1,
        "OWN": 10,
        "STRENGTH": 3,
        "EXHAUSTED": 1,
        "MANNER": 2,
        "ADDRESSED": 2,
        "IMPRESSIVE": 1,
        "DEPARTED": 2,
        "LAND": 4,
        "CANNOT": 2,
        "GUESS": 2,
        "HOW": 14,
        "MANY": 8,
        "DAYS": 4,
        "SINCE": 5,
        "ENDURED": 2,
        "MISERY": 1,
        "NOTHING": 6,
        "ETERNAL": 1,
        "SENTIMENT": 1,
        "RESERVED": 1,
        "VENGEANCE": 2,
        "LAUGHTER": 2,
        "DIED": 1,
        "KNOWN": 4,
        "ABHORRED": 2,
        "APPARENTLY": 2,
        "EAR": 1,
        "SCARED": 1,
        "HORRID": 1,
        "APPARITION": 1,
        "INFORMED": 1,
        "PATH": 2,
        "SOMETIMES": 6,
        "WHO": 20,
        "FEARED": 2,
        "LOST": 4,
        "TRACE": 2,
        "DESPAIR": 1,
        "DIE": 4,
        "SOME": 17,
        "MARK": 2,
        "GUIDE": 1,
        "SAW": 11,
        "OPEN": 7,
        "FIGURE": 1,
        "MOST": 15,
        "HIDEOUS": 1,
        "GRIN": 1,
        "FACE": 7,
        "MONSTER": 2,
        "SEEMED": 4,
        "JEER": 1,
        "FIENDISH": 1,
        "FINGER": 2,
        "POINTED": 1,
        "TOWARDS": 3,
        "CORPSE": 1,
        "WIFE": 4,
        "WHOM": 9,
        "CREATED": 1,
        "MISERABLE": 1,
        "SENT": 7,
        "ABROAD": 3,
        "WORLD": 6,
        "DESTRUCTION": 1,
        "POSSESSED": 1,
        "MADDENING": 1,
        "RAGE": 1,
        "BEGINNING": 1,
        "RISE": 1,
        "SUDDENLY": 5,
        "HEAVY": 3,
        "STORM": 2,
        "RAIN": 2,
        "DESCENDED": 1,
        "CALM": 2,
        "OBSCURED": 1,
        "SHAPES": 1,
        "OBJECTS": 1,
        "HARDSHIPS": 1,
        "TRAVELLERS": 1,
        "DESERTS": 1,
        "BARBAROUS": 1,
        "COUNTRIES": 1,
        "WONT": 1,
        "MEET": 2,
        "LIVED": 3,
        "HARDLY": 1,
        "PROVIDED": 2,
        "SUM": 1,
        "MONEY": 5,
        "TOGETHER": 5,
        "JEWELS": 1,
        "BELONGED": 1,
        "MOTHER": 3,
        "NOW": 24,
        "WANDERINGS": 1,
        "BEGAN": 5,
        "CEASE": 1,
        "LIFE": 7,
        "OTHERWISE": 3,
        "FOREVER": 1,
        "CALL": 4,
        "SPIRITS": 2,
        "DEAD": 3,
        "WANDERING": 1,
        "MINISTERS": 1,
        "AID": 2,
        "CONDUCT": 1,
        "SENSE": 2,
        "SHAME": 3,
        "ANGER": 1,
        "OR": 22,
        "OTHER": 18,
        "CAUSE": 1,
        "FLEEING": 1,
        "IMMATERIAL": 1,
        "THING": 8,
        "QUICKENED": 1,
        "POWER": 2,
        "ACCUSATION": 1,
        "PICTURE": 2,
        "FRESH": 3,
        "OBLONG": 1,
        "EXCAVATION": 1,
        "SOIL": 1,
        "FAMILY": 2,
        "BURIAL": 1,
        "GROUND": 4,
        "DULL": 1,
        "THUD": 1,
        "EARTH": 2,
        "FALLING": 1,
        "REGULARLY": 2,
        "LISTENING": 3,
        "LABOUR": 1,
        "MEN": 7,
        "GIVEN": 1,
        "UNCOUTH": 1,
        "RHYTHM": 1,
        "THEIR": 34,
        "GRUNTING": 1,
        "EXPULSIONS": 1,
        "BREATH": 3,
        "NATURE": 6,
        "INDUSTRY": 1,
        "SURROUNDINGS": 1,
        "IMPOSED": 1,
        "UPON": 12,
        "WE": 44,
        "GRANTED": 1,
        "FIND": 8,
        "NECESSARY": 4,
        "STAY": 3,
        "SMITHTOWN": 2,
        "WHILE": 8,
        "SHE": 41,
        "HAUNTED": 1,
        "DREAD": 1,
        "NEVER": 7,
        "SEE": 12,
        "HER": 43,
        "HUSBAND": 1,
        "ALIVE": 1,
        "NEXT": 1,
        "DAYLIGHT": 2,
        "WHOLE": 4,
        "NEIGHBORHOOD": 1,
        "ASTIR": 1,
        "ROUND": 3,
        "CAREFULLY": 2,
        "SEARCHED": 1,
        "ANY": 9,
        "MISSING": 1,
        "BARS": 1,
        "THINGS": 7,
        "FOUND": 10,
        "HARBORS": 1,
        "HOTELS": 1,
        "FENCES": 1,
        "PRISONS": 1,
        "COURTS": 2,
        "MUSIC": 1,
        "OFF": 7,
        "DOCTOR": 5,
        "SCOTT": 1,
        "LOCAL": 1,
        "CORONER": 1,
        "HELD": 3,
        "READINESS": 1,
        "SUMMON": 1,
        "CORONER'S": 1,
        "JURY": 1,
        "SHORTEST": 1,
        "NOTICE": 2,
        "MEASURES": 1,
        "PROVED": 1,
        "UNAVAILING": 1,
        "PUBLIC": 1,
        "MEETING": 1,
        "INHABITANTS": 2,
        "CONVENED": 1,
        "FUNDS": 1,
        "SUBSCRIBED": 1,
        "STILL": 7,
        "FURTHER": 2,
        "PROSECUTE": 1,
        "SEARCH": 2,
        "GLANCING": 1,
        "BOBBY": 4,
        "ASKED": 6,
        "HOLLOW": 1,
        "SCORN": 1,
        "YOU'VE": 3,
        "NO": 32,
        "OBJECTION": 2,
        "GENTLEMAN": 1,
        "VISITING": 1,
        "PRESENT": 1,
        "WISHES": 1,
        "ANSWERED": 5,
        "CAN": 13,
        "OUTSIDE": 2,
        "SHORT": 1,
        "RED": 3,
        "STEER": 1,
        "INSIDE": 4,
        "LONG": 9,
        "BLACK": 2,
        "BOTTLE": 1,
        "BRASS": 2,
        "BAND": 1,
        "CLEVER": 1,
        "THOUGH": 5,
        "SOMEWHAT": 2,
        "COMPLICATED": 1,
        "ARRANGEMENT": 1,
        "HOLDING": 1,
        "CROWD": 1,
        "BRICK": 1,
        "ADMIRABLE": 4,
        "PERSON": 1,
        "MADE": 15,
        "RIGHT": 8,
        "SORT": 6,
        "CLAY": 1,
        "POSSESSING": 1,
        "PLENTY": 2,
        "SAND": 1,
        "OVERCOAT": 2,
        "I'VE": 3,
        "NEARLY": 5,
        "FROZEN": 1,
        "DRIVING": 2,
        "BEFORE": 14,
        "EITHER": 2,
        "GROPE": 2,
        "SUITABLE": 2,
        "GREETING": 2,
        "FACED": 2,
        "ROBINSON": 1,
        "JERKED": 1,
        "HEAD": 4,
        "TOWARD": 2,
        "WATCHING": 3,
        "PREPARATIONS": 1,
        "THERE": 29,
        "HENCE": 2,
        "UNATTACHED": 1,
        "LADY": 7,
        "MAY": 13,
        "STICK": 2,
        "GET": 4,
        "STUCK": 1,
        "BACKBITER": 1,
        "MOSQUITO": 1,
        "BALANCE": 2,
        "SOMETHING": 10,
        "WANTED": 4,
        "BOOK": 2,
        "KEEPERS": 1,
        "OFTEN": 2,
        "TOPERS": 1,
        "HANDED": 1,
        "BANKNOTE": 1,
        "DIDN'T": 2,
        "MISS": 4,
        "GRAHAM'S": 1,
        "MEANING": 2,
        "GLANCE": 1,
        "DEPOSITED": 1,
        "DRY": 2,
        "PATCH": 1,
        "NEAR": 6,
        "EDGE": 2,
        "MORASS": 1,
        "LITTLE": 15,
        "INTERIOR": 1,
        "MAN'S": 3,
        "COAT": 3,
        "DARK": 3,
        "BROWN": 2,
        "STUFF": 1,
        "WHY": 5,
        "FAIL": 1,
        "REFER": 1,
        "BOBBY'S": 1,
        "QUESTIONS": 1,
        "MOMENT": 5,
        "ARREST": 1,
        "OPENLY": 1,
        "EXPRESSED": 1,
        "ENMITY": 1,
        "GRAHAM": 1,
        "ONLY": 14,
        "THEORY": 1,
        "PROMISED": 2,
        "FIT": 1,
        "PANAMANIAN": 1,
        "RETURN": 3,
        "CEDARS": 1,
        "HATRED": 1,
        "KIND": 3,
        "ANIMAL": 1,
        "ANCIENTS": 1,
        "CATALOGUED": 1,
        "UNDER": 6,
        "HEADS": 3,
        "HYENA": 1,
        "BAD": 3,
        "THOUGHTS": 1,
        "BESET": 1,
        "PROPERLY": 1,
        "LUMINOUS": 2,
        "RING": 1,
        "ENCIRCLING": 1,
        "ASTRONOMICAL": 1,
        "BODY": 1,
        "INFREQUENTLY": 1,
        "CONFOUNDED": 2,
        "AUREOLA": 1,
        "NIMBUS": 1,
        "SIMILAR": 1,
        "PHENOMENON": 1,
        "WORN": 1,
        "DRESS": 4,
        "DIVINITIES": 1,
        "SAINTS": 1,
        "FURRIER": 1,
        "GETS": 1,
        "SKINS": 1,
        "MORE": 15,
        "FOXES": 1,
        "THAN": 14,
        "ASSES": 1,
        "CUPID": 1,
        "THEREFORE": 5,
        "CERTAINTY": 1,
        "PHILOSOPHER": 1,
        "HAS": 11,
        "YET": 5,
        "CAT": 4,
        "LIFT": 1,
        "NODDLE": 1,
        "FEED": 1,
        "FIDDLE": 1,
        "FADDLE": 1,
        "FLUMMERY": 1,
        "UNSWADDLE": 1,
        "NEW": 7,
        "BORN": 1,
        "SELF": 2,
        "SUFFICIENCY": 1,
        "MOCKERY": 1,
        "AFFLICTED": 1,
        "IMPEDIMENT": 1,
        "ONE'S": 2,
        "REACH": 2,
        "OFFICER": 2,
        "LAW": 2,
        "CHARGED": 1,
        "DUTIES": 1,
        "HIGHEST": 1,
        "DIGNITY": 1,
        "UTMOST": 1,
        "GRAVITY": 2,
        "HEREDITARY": 1,
        "DISESTEEM": 1,
        "POPULACE": 1,
        "CRIMINAL": 2,
        "ANCESTRY": 1,
        "PROFESSOR": 3,
        "GRAYBILL": 1,
        "ABOUT": 11,
        "DOGS": 3,
        "B": 2,
        "ARITHMETIC": 1,
        "CHILDHOOD": 1,
        "CALLED": 5,
        "ALSO": 11,
        "HEN": 2,
        "HERMIT": 1,
        "INGENIOUS": 1,
        "DEVICE": 2,
        "OBTAINING": 1,
        "INDIVIDUAL": 2,
        "PROFIT": 1,
        "RESPONSIBILITY": 1,
        "CORSAIR": 1,
        "EXPOUNDED": 1,
        "CONVINCING": 1,
        "LUCIDITY": 1,
        "CHAIRS": 2,
        "ACROBATIC": 1,
        "WAVERING": 1,
        "FLOORS": 1,
        "MATTRESS": 1,
        "KICKS": 1,
        "PILLOW": 2,
        "SNORES": 1,
        "SONS": 2,
        "CUPIDITY": 1,
        "CRADLED": 1,
        "SIN": 1,
        "RANKS": 1,
        "ANGEL": 1,
        "THIN": 2,
        "AVENGING": 1,
        "FRIEND": 2,
        "COULDN'T": 3,
        "ACCOUNT": 1,
        "FOULNESS": 1,
        "BROOKS": 1,
        "THOMAS": 1,
        "M": 1,
        "MARY": 2,
        "FRAZER": 1,
        "SERVICEABLE": 1,
        "IMMORTAL": 1,
        "ADDITION": 2,
        "PHRASEOLOGY": 1,
        "ENGLISH": 1,
        "TONGUE": 1,
        "HAG": 1,
        "ROAD": 2,
        "DIM": 1,
        "BLENDED": 1,
        "BLUE": 3,
        "MELODY": 1,
        "SONGSTER": 1,
        "FOWL": 1,
        "ESTEEMED": 2,
        "CAGE": 1,
        "FULL": 3,
        "CHORUS": 1,
        "DRAW": 3,
        "TEARS": 3,
        "TWO": 11,
        "PERSONS": 1,
        "ONCE": 8,
        "SCIENTIFIC": 1,
        "DICKY": 1,
        "BIRD": 1,
        "PORCUS": 1,
        "ROCKEFELLERI": 1,
        "COMMONLY": 1,
        "PLAIN": 2,
        "UNMISTAKABLE": 2,
        "REMINDER": 1,
        "DUE": 2,
        "COURSE": 4,
        "APPOINTED": 1,
        "PRIOR": 1,
        "FORGOTTEN": 2,
        "LORD": 1,
        "DILWORTH": 2,
        "ROBBED": 1,
        "TREASURE": 2,
        "FIRM": 1,
        "FAST": 5,
        "LENGTHENED": 1,
        "PERIOD": 1,
        "NINE": 1,
        "YIELDED": 3,
        "UP": 17,
        "HEARTS": 1,
        "SORROW": 1,
        "DUNFERN": 1,
        "EVER": 8,
        "DREAM": 1,
        "APOLOGY": 1,
        "DISOBEDIENCE": 1,
        "DILWORTH'S": 1,
        "ORDERS": 2,
        "ARRAYING": 1,
        "HERSELF": 3,
        "GARB": 1,
        "GLISTENING": 1,
        "GLORY": 1,
        "ACCEPTED": 1,
        "EVEN": 12,
        "LOVING": 1,
        "RUSHED": 3,
        "AMONGST": 1,
        "SHOUTING": 2,
        "HIT": 3,
        "HEW": 1,
        "FOUR": 6,
        "BLAST": 1,
        "BORE": 1,
        "EVERY": 9,
        "RHYME": 1,
        "DOWN": 14,
        "GREAT": 7,
        "STAMP": 7,
        "FOOT": 4,
        "CUTTING": 2,
        "SAME": 9,
        "TIME": 18,
        "FACES": 1,
        "EXECUTING": 1,
        "INDEED": 6,
        "SWORD": 1,
        "DANCE": 2,
        "WILDEST": 1,
        "DESCRIPTION": 1,
        "INVULNERABLE": 1,
        "QUEEN": 2,
        "ATTACKED": 1,
        "LEGS": 5,
        "FEET": 9,
        "HORRIBLE": 1,
        "GRANITE": 1,
        "SHOE": 2,
        "CAPTAIN": 4,
        "GOT": 13,
        "BACK": 6,
        "STOOD": 6,
        "LONGER": 5,
        "DRESSING": 2,
        "LEG": 3,
        "RUBBED": 1,
        "SMELT": 1,
        "LIKE": 12,
        "ROSES": 1,
        "WAVED": 1,
        "HANDS": 4,
        "OVER": 9,
        "TIMES": 2,
        "LAST": 7,
        "WAVE": 1,
        "VANISHED": 1,
        "FELT": 2,
        "SINKING": 1,
        "PROFOUNDEST": 1,
        "SLUMBER": 1,
        "PUNCTILIOUS": 2,
        "UNFORTUNATE": 1,
        "GAVE": 2,
        "RECEIVE": 1,
        "MARKS": 1,
        "RESPECT": 2,
        "PAID": 2,
        "DECEASED": 1,
        "APPLAUSE": 2,
        "STOICAL": 1,
        "SEEMS": 3,
        "STRONGLY": 1,
        "MOVED": 3,
        "DEAR": 9,
        "NATIVE": 1,
        "IMMENSE": 1,
        "POPULARITY": 1,
        "ENGLAND": 3,
        "SPOKE": 3,
        "COLD": 2,
        "DISDAIN": 1,
        "IRENE": 1,
        "AROUSED": 1,
        "RINGING": 1,
        "BREAKFAST": 2,
        "BELL": 1,
        "FINISH": 1,
        "SENTENCE": 2,
        "TROUBLED": 2,
        "WEARY": 1,
        "BRAIN": 1,
        "MONTHS": 1,
        "FRANTIC": 1,
        "EXPERTNESS": 1,
        "DASHED": 1,
        "WINDING": 2,
        "STAIRCASE": 1,
        "SUMPTUOUS": 1,
        "FURNITURE": 3,
        "HASTILY": 1,
        "NURSERY": 1,
        "PRINCE": 4,
        "WALES": 2,
        "FURNISHED": 1,
        "INFANT": 1,
        "REQUIRE": 1,
        "ATTENDANTS": 1,
        "PRESENTED": 1,
        "KEY": 1,
        "SUPERB": 1,
        "CASKET": 1,
        "APARTMENT": 2,
        "CURDIE": 2,
        "WITHIN": 1,
        "PACES": 1,
        "OPPOSING": 1,
        "HAPPILY": 2,
        "WITHDREW": 1,
        "CAUGHT": 3,
        "WAIST": 1,
        "DASH": 1,
        "MARBLE": 2,
        "FLOOR": 2,
        "HALL": 1,
        "EMPTY": 2,
        "GOBLINS": 2,
        "RUNNING": 3,
        "HOWLING": 2,
        "SHRIEKING": 1,
        "LIMPING": 1,
        "COWERING": 1,
        "RAN": 3,
        "CUDDLE": 1,
        "WOUNDED": 1,
        "HARD": 1,
        "PROTECT": 1,
        "FRIGHTFUL": 1,
        "ARMED": 1,
        "LIFTED": 2,
        "PROSTRATE": 1,
        "PRESSED": 1,
        "MOMENTS": 2,
        "RECOVERED": 1,
        "CONSCIOUSNESS": 1,
        "WHERE'S": 1,
        "PRINCESS": 1,
        "CRIED": 12,
        "KNEW": 7,
        "SHOUTED": 3,
        "DISAPPEARING": 1,
        "HOLE": 2,
        "RATS": 1,
        "MICE": 1,
        "HOWEVER": 6,
        "CERTAIN": 2,
        "POSEIDON": 1,
        "WATCH": 1,
        "ALONE": 1,
        "MATTERS": 3,
        "HOME": 4,
        "COME": 9,
        "SUBSTANCE": 1,
        "BEING": 13,
        "WASTED": 1,
        "H": 2,
        "O": 3,
        "AMONG": 2,
        "VOWELS": 1,
        "FEMININES": 1,
        "EQUAL": 1,
        "NUMBER": 3,
        "MASCULINE": 1,
        "FEMININE": 1,
        "MAINTAIN": 2,
        "TRAGEDY": 2,
        "PRIMARILY": 1,
        "IMITATION": 1,
        "ACTION": 2,
        "MAINLY": 1,
        "SAKE": 1,
        "IMITATES": 1,
        "PERSONAL": 2,
        "AGENTS": 1,
        "THIRD": 4,
        "COMES": 1,
        "ELEMENT": 1,
        "POLEOS": 1,
        "PELEIADEO": 1,
        "PELEIDON": 1,
        "CURTAILED": 1,
        "PART": 1,
        "SAY": 15,
        "WORSHIP": 2,
        "ENTIRELY": 2,
        "SANCHO": 1,
        "ASS": 2,
        "MOUTH": 4,
        "ROPE": 1,
        "STORY": 6,
        "HERACLES": 1,
        "HOMER": 1,
        "EVIDENTLY": 2,
        "UNDERSTOOD": 1,
        "POINT": 3,
        "QUITE": 6,
        "WHETHER": 3,
        "ART": 3,
        "INSTINCT": 1,
        "WAY": 2,
        "EXCELS": 1,
        "REST": 2,
        "END": 4,
        "NATURALLY": 1,
        "ITSELF": 2,
        "USUAL": 2,
        "CONSEQUENT": 1,
        "ELSE": 1,
        "MIDDLE": 1,
        "NEWS": 5,
        "DESIRES": 1,
        "DESERVES": 2,
        "LET": 9,
        "DULCINEA": 1,
        "LOOK": 6,
        "DOES": 3,
        "ANSWER": 2,
        "REASONABLY": 1,
        "OFFERED": 1,
        "SACRIFICE": 3,
        "SPIRITED": 1,
        "SACRIFICERS": 1,
        "ANOTHER": 11,
        "WHERE": 8,
        "CUSTOM": 1,
        "STRANGERS": 1,
        "GODDESS": 1,
        "PRIESTESS": 1,
        "RITE": 1,
        "UNITY": 2,
        "PLOT": 2,
        "CONSIST": 1,
        "SUPPOSE": 2,
        "SUBJECT": 1,
        "INFINITY": 1,
        "BEFALL": 1,
        "IMPOSSIBLE": 1,
        "REDUCE": 1,
        "CONSTRUCTION": 1,
        "EARLY": 2,
        "DRAMATISTS": 1,
        "ESSENTIAL": 1,
        "SOUL": 2,
        "SPEAK": 4,
        "LETTERS": 1,
        "DIFFER": 1,
        "VARIOUS": 1,
        "WAYS": 2,
        "PRODUCED": 1,
        "DIFFERENT": 3,
        "CONFORMATIONS": 1,
        "REGIONS": 1,
        "ASPIRATED": 2,
        "LIMIT": 1,
        "SET": 3,
        "ACTUAL": 1,
        "CONSISTENTLY": 1,
        "COMPREHENSIBLE": 1,
        "FINER": 1,
        "REASON": 2,
        "MAGNITUDE": 1,
        "ROUGH": 2,
        "GENERAL": 2,
        "FORMULA": 1,
        "POOR": 1,
        "FELLOW": 4,
        "THOU": 3,
        "HAST": 2,
        "BELABORED": 1,
        "COUNTED": 1,
        "BEST": 6,
        "HAND": 10,
        "QUARTERSTAFF": 2,
        "MERRY": 1,
        "JOHN": 6,
        "MINE": 2,
        "ROBIN": 2,
        "HOOD": 2,
        "YOUTH": 2,
        "PEASANT": 1,
        "WHOSE": 3,
        "UNABLE": 1,
        "LEANING": 2,
        "FORWARD": 3,
        "BATHING": 2,
        "BROOK": 1,
        "FLOWED": 1,
        "PAST": 3,
        "APPROACHED": 2,
        "SILENTLY": 1,
        "PERCEIVE": 1,
        "FULLY": 1,
        "OCCUPIED": 1,
        "INNS": 1,
        "KNOWEST": 1,
        "HEREABOUTS": 1,
        "WEARIED": 1,
        "CHILD": 2,
        "HEIR": 1,
        "AFFECTIONATE": 1,
        "PARENTS": 2,
        "INDULGED": 2,
        "DAUGHTERS": 2,
        "FORTUNATE": 1,
        "DARING": 1,
        "KNIGHT": 1,
        "DON": 1,
        "QUIXOTE": 1,
        "LA": 1,
        "MANCHA": 1,
        "ENTREATED": 1,
        "ACCOMPANY": 1,
        "CITY": 4,
        "VASSALS": 1,
        "TOLD": 4,
        "BEAUTY": 2,
        "SUCH": 4,
        "BLIND": 1,
        "BEGGED": 1,
        "ANYTHING": 4,
        "CONCERNING": 1,
        "TELL": 12,
        "FORTUNE": 2,
        "BLESSING": 1,
        "COURAGE": 1,
        "BEAR": 2,
        "WHATEVER": 1,
        "CALAMITY": 1,
        "FALL": 3,
        "SURE": 3,
        "NONE": 3,
        "CAPABLE": 1,
        "INCREASING": 1,
        "DEGREE": 1,
        "ALREADY": 6,
        "TAKING": 2,
        "STOUT": 2,
        "PIKESTAFF": 1,
        "FORTH": 1,
        "JOURNEY": 1,
        "GOOD": 11,
        "TOWN": 7,
        "BLYTH": 1,
        "TANNER": 1,
        "CELEBRATED": 1,
        "FAR": 2,
        "FEATS": 1,
        "TOUGH": 1,
        "BOUTS": 1,
        "WRESTLING": 1,
        "BRIDEGROOM": 1,
        "APPROACHING": 2,
        "UNLACE": 1,
        "BOSOM": 1,
        "GIVE": 3,
        "AIR": 5,
        "NOTTINGHAMSHIRE": 1,
        "DONE": 8,
        "BURSTING": 1,
        "THICKET": 1,
        "TILL": 2,
        "CHEEKS": 1,
        "BIDED": 1,
        "BOAR": 1,
        "INN": 1,
        "UNTIL": 2,
        "ILL": 1,
        "PIECE": 2,
        "LUCK": 1,
        "DUTY": 1,
        "PLEASURE": 3,
        "SCORE": 1,
        "APT": 1,
        "CASE": 2,
        "CRUSH": 3,
        "CLODS": 1,
        "FOLLOW": 2,
        "PLOUGH": 1,
        "OXEN": 1,
        "OWNER'S": 1,
        "SUGGESTED": 2,
        "FINDING": 1,
        "NOTICED": 2,
        "CURATE": 1,
        "FRONT": 1,
        "SIGN": 1,
        "CONCEAL": 1,
        "THEMSELVES": 3,
        "BEHIND": 1,
        "ROCK": 1,
        "LAY": 4,
        "BATS": 1,
        "FLEW": 1,
        "DOVES": 1,
        "DOVE": 2,
        "COTE": 1,
        "LOWER": 1,
        "WINDOWS": 2,
        "VERY": 20,
        "HIGH": 3,
        "NARROW": 2,
        "CHANGING": 1,
        "LIGHT": 5,
        "FIRE": 4,
        "GLIMMER": 1,
        "SEEING": 1,
        "FEARING": 1,
        "CREATURES": 1,
        "BONES": 1,
        "IMAGINED": 2,
        "NECKS": 1,
        "QUEER": 1,
        "BESIDES": 3,
        "MUSEUM": 1,
        "NATURAL": 1,
        "HISTORY": 2,
        "SAINT": 2,
        "PETER'S": 1,
        "CHURCH": 1,
        "VISITED": 2,
        "BEWILDERS": 1,
        "HELP": 6,
        "COUNT": 1,
        "THOSE": 1,
        "VAN": 1,
        "MOUNEN": 1,
        "WANT": 3,
        "BIG": 6,
        "ITEM": 1,
        "NOTEBOOK": 1,
        "CAREFUL": 3,
        "RECKONING": 1,
        "TOWER": 1,
        "HIGHER": 2,
        "CENTURIES": 1,
        "AGO": 3,
        "BELEAGUERED": 1,
        "LEYDEN": 1,
        "WATCHER": 1,
        "TOP": 1,
        "WILD": 2,
        "DESPAIRING": 1,
        "CRIES": 1,
        "WATERS": 2,
        "RISING": 1,
        "MEANTIME": 1,
        "SUPERVISOR": 1,
        "RODE": 1,
        "KITT'S": 1,
        "DISMOUNT": 1,
        "DINGLE": 1,
        "LEADING": 1,
        "SUPPORTING": 1,
        "HORSES": 1,
        "CONTINUAL": 1,
        "FEAR": 4,
        "AMBUSHES": 1,
        "CONTAINING": 1,
        "LUZAC'S": 1,
        "MEMORIAL": 1,
        "BOERHAAVE'S": 1,
        "MONUMENT": 1,
        "WHITE": 3,
        "URN": 1,
        "CARVED": 2,
        "SYMBOLS": 1,
        "AGES": 2,
        "MEDALLION": 1,
        "BOERHAAVE": 1,
        "ADORNED": 1,
        "FAVORITE": 2,
        "MOTTO": 1,
        "HAWKINS": 2,
        "SIR": 5,
        "REPLIED": 3,
        "CAN'T": 5,
        "SCATTER": 1,
        "OH": 4,
        "SHIVER": 1,
        "STONE": 1,
        "LYING": 2,
        "PUT": 6,
        "PUSH": 1,
        "BULLET": 1,
        "WHISTLED": 1,
        "ARM": 1,
        "LUGGER": 1,
        "DOUBLED": 1,
        "DISAPPEARED": 3,
        "MISTER": 5,
        "FISH": 2,
        "WATER": 5,
        "HOUSE": 4,
        "MUCKLE": 1,
        "AY": 1,
        "FOLK": 2,
        "BRIGHT": 2,
        "LIGHTS": 1,
        "SHOW": 2,
        "MILE": 1,
        "DOOR": 3,
        "BEGGAR'S": 1,
        "KNOCK": 1,
        "CAUTIOUSLY": 1,
        "BETTER": 5,
        "VENTURESOME": 1,
        "TUMBLE": 1,
        "HORROR": 1,
        "MEAN": 3,
        "CRASHING": 1,
        "BEN": 1,
        "STIR": 1,
        "GASP": 1,
        "JACOB": 2,
        "STARTLED": 1,
        "PERPLEXING": 1,
        "LANGUAGE": 3,
        "SURELY": 3,
        "SLIPSHOD": 1,
        "SYSTEMLESS": 1,
        "SLIPPERY": 1,
        "ELUSIVE": 1,
        "GRASP": 1,
        "WASHED": 1,
        "WEARING": 1,
        "EMBROIDERED": 2,
        "COURT": 1,
        "UNIFORM": 1,
        "KNEE": 1,
        "BREECHES": 1,
        "SHOES": 1,
        "STARS": 2,
        "BREAST": 2,
        "SERENE": 1,
        "EXPRESSION": 1,
        "FLAT": 1,
        "REFINED": 1,
        "FRENCH": 2,
        "OUR": 10,
        "GRANDFATHERS": 1,
        "INHUMANLY": 1,
        "TREATED": 2,
        "BERKELEY": 1,
        "CASTLE": 1,
        "WHITHER": 1,
        "ENDS": 1,
        "SAD": 2,
        "MONARCH": 2,
        "MINOR": 1,
        "POSITION": 2,
        "FARM": 1,
        "BEASTLY": 1,
        "FLUKE": 1,
        "KING": 2,
        "BUSINESS": 1,
        "LEARNING": 1,
        "MAKES": 2,
        "KIN": 1,
        "PROVERBS": 1,
        "DRESSED": 1,
        "SIMPLE": 2,
        "MUSLIN": 1,
        "SINGLE": 2,
        "TUBEROSE": 1,
        "AMPLE": 1,
        "FOLDS": 1,
        "RICH": 2,
        "HAIR": 3,
        "TOTTERED": 1,
        "FEEBLY": 1,
        "STAIRS": 2,
        "PALE": 1,
        "TERROR": 1,
        "EXCITEMENT": 2,
        "COPERNICUS": 1,
        "FROWNED": 1,
        "FATHER": 7,
        "EDUCATION": 1,
        "TURNED": 2,
        "FOOLS": 1,
        "HIPPOLYTE": 1,
        "LEAST": 1,
        "QUIET": 3,
        "FOOL": 2,
        "MOONLIGHT": 1,
        "FROLIC": 1,
        "EDWARD": 1,
        "FLED": 2,
        "SERVING": 1,
        "MEASURE": 1,
        "VISIBLE": 1,
        "PHENOMENA": 1,
        "ASTRONOMY": 1,
        "STARTS": 1,
        "MET": 2,
        "COUNSELOR'S": 1,
        "STREET": 5,
        "MIDST": 2,
        "UNDERTAKING": 1,
        "HALTS": 1,
        "PEOPLE": 4,
        "STAND": 2,
        "SIT": 3,
        "JULY": 1,
        "EIGHTEEN": 1,
        "FIVE": 2,
        "SPEAKER": 1,
        "ANNA": 3,
        "PAVLOVNA": 2,
        "SCHERER": 1,
        "MAID": 2,
        "HONOR": 1,
        "EMPRESS": 1,
        "MARYA": 1,
        "FEDOROVNA": 1,
        "WORDS": 2,
        "GREETED": 1,
        "VASILI": 1,
        "KURAGIN": 1,
        "HYPHENS": 1,
        "TREATS": 1,
        "FOURTEEN": 1,
        "FIFTEEN": 2,
        "SUBJECTS": 1,
        "EACH": 4,
        "ENCLOSED": 1,
        "PARENTHESIS": 1,
        "EXTRA": 1,
        "PARENTHESES": 1,
        "LISTEN": 1,
        "ANNETTE": 1,
        "PAVLOVNA'S": 1,
        "DRAWING": 1,
        "DOWNWARDS": 1,
        "ARRANGE": 1,
        "AFFAIR": 1,
        "DEVOTED": 2,
        "SLAVE": 1,
        "NOR": 4,
        "CONSIDERED": 2,
        "CORRECT": 1,
        "CONVERSATION": 3,
        "POLITICAL": 1,
        "BURST": 2,
        "DON'T": 7,
        "AUSTRIA": 1,
        "PERHAPS": 9,
        "UNDERSTAND": 1,
        "ISN'T": 3,
        "DROWNED": 3,
        "PORPOISES": 2,
        "DEEP": 3,
        "DECAPODS": 1,
        "HEAR": 3,
        "SALT": 2,
        "SHELL": 1,
        "US": 14,
        "OCEAN": 1,
        "GOSSIPS": 1,
        "BOY": 8,
        "SORRY": 1,
        "UNCLE": 2,
        "LOOKED": 6,
        "CUPBOARDS": 1,
        "DRAWERS": 1,
        "LOCKERS": 1,
        "CHESTS": 1,
        "SHIP'S": 1,
        "DINING": 2,
        "ROOM": 8,
        "EVERYWHERE": 1,
        "DOING": 3,
        "LOT": 1,
        "WONDERFUL": 2,
        "PIRATES": 2,
        "STOLEN": 1,
        "SHIPS": 1,
        "THAT'S": 2,
        "WE'LL": 1,
        "GO": 10,
        "TEA": 2,
        "STRAWBERRY": 1,
        "JAM": 1,
        "DAB": 2,
        "PETS": 2,
        "DUCKS": 1,
        "ANIMALS": 2,
        "STRANGE": 1,
        "LOOKING": 2,
        "UPHELD": 1,
        "LEARNED": 1,
        "TRUE": 5,
        "RECKONED": 1,
        "NIGH": 1,
        "FALSE": 3,
        "PROBABLE": 2,
        "SCIENCES": 1,
        "EARNEST": 1,
        "DESIRE": 1,
        "DISTINGUISH": 1,
        "ORDER": 2,
        "ABLE": 4,
        "CLEARLY": 1,
        "DISCRIMINATE": 1,
        "PROCEED": 1,
        "CONFIDENCE": 2,
        "THEY'RE": 1,
        "HEARERS": 1,
        "TREATING": 1,
        "BRANCHES": 1,
        "CURIOUS": 2,
        "RARE": 1,
        "JUDGMENT": 2,
        "OTHERS": 3,
        "FORMED": 1,
        "INFERIOR": 2,
        "FELLOWS": 1,
        "FLOWERS": 1,
        "GOLD": 2,
        "JARS": 1,
        "FINE": 3,
        "TOBACCO": 1,
        "JAMAICA": 1,
        "IVORY": 1,
        "BOXES": 3,
        "RUSSIAN": 1,
        "OLD": 8,
        "VIOLIN": 1,
        "STRING": 4,
        "BROKEN": 1,
        "YES": 5,
        "WENT": 11,
        "DOWNSTAIRS": 1,
        "BEAUTIFUL": 3,
        "SHIP": 2,
        "GATHERED": 3,
        "TALKING": 1,
        "TRYING": 2,
        "NOWHERE": 2,
        "SEEN": 4,
        "WOULDN'T": 1,
        "MUCH": 7,
        "AFRAID": 4,
        "FOSTER": 1,
        "VANITY": 1,
        "REMOTE": 1,
        "COMMON": 1,
        "REQUIRING": 1,
        "GREATER": 2,
        "INGENUITY": 1,
        "RENDER": 1,
        "FELL": 3,
        "MESSENE": 1,
        "ORTILOCHUS": 1,
        "BIDDEN": 1,
        "ULYSSES": 5,
        "THOROUGHLY": 2,
        "PURIFIED": 1,
        "CLOISTERS": 1,
        "INNER": 1,
        "WOMEN": 2,
        "HAPPENED": 2,
        "WHEREON": 1,
        "MELANTHIUS": 1,
        "HELMET": 1,
        "ROTTED": 1,
        "SHIELD": 1,
        "PAVEMENT": 1,
        "TRIAL": 1,
        "BOW": 3,
        "THRICE": 2,
        "TUG": 1,
        "NOBLE": 3,
        "BIRTH": 1,
        "APOLLO": 2,
        "LIVE": 1,
        "WIDOW": 1,
        "SWINEHERD": 1,
        "BESIDE": 2,
        "DESERVE": 1,
        "THANKS": 1,
        "STERNLY": 1,
        "SACRIFICING": 1,
        "PRIEST": 1,
        "PRAYED": 1,
        "SHED": 1,
        "ARROWS": 1,
        "CONTEST": 1,
        "VOUCHSAFE": 1,
        "TELEMACHUS": 1,
        "STORE": 1,
        "ARMOUR": 1,
        "CHOSE": 1,
        "SHIELDS": 1,
        "EIGHT": 2,
        "SPEARS": 1,
        "HELMETS": 1,
        "HORSE": 5,
        "PLUMES": 1,
        "SPEED": 1,
        "GRIEVE": 1,
        "FORGO": 1,
        "MARRIAGE": 1,
        "CARE": 1,
        "ITHACA": 1,
        "ELSEWHERE": 1,
        "FEEL": 2,
        "FACT": 3,
        "EXPECTING": 1,
        "SHOOT": 1,
        "WINE": 1,
        "MISCHIEF": 1,
        "ACCEPT": 1,
        "INVITATION": 1,
        "OZ": 1,
        "CONGENIAL": 2,
        "COMPANY": 1,
        "ACKNOWLEDGED": 2,
        "PUMPKINHEAD": 5,
        "FLIES": 1,
        "HONEY": 1,
        "SUIT": 2,
        "EXTRAORDINARY": 1,
        "IDEA": 3,
        "EMPEROR": 2,
        "SHOCKED": 1,
        "MAJESTY": 2,
        "COMPANIONS": 1,
        "SCARECROW": 7,
        "POLITENESS": 1,
        "INTRODUCED": 1,
        "TIP": 5,
        "JACK": 2,
        "LATTER": 1,
        "PERSONAGE": 2,
        "INTEREST": 2,
        "TIN": 2,
        "WOODMAN": 2,
        "GREATLY": 1,
        "BEG": 2,
        "SPEECH": 1,
        "SHARPLY": 1,
        "REMEMBER": 3,
        "PLEASE": 1,
        "ABUSING": 2,
        "FORGET": 2,
        "RETORTED": 1,
        "GATEWAY": 1,
        "PROPOSED": 1,
        "ESCAPE": 2,
        "ROYAL": 1,
        "ARMY": 5,
        "LED": 1,
        "ALONG": 1,
        "PASSAGE": 2,
        "SMARTED": 1,
        "AFTERWARD": 1,
        "NEEDLES": 2,
        "EFFECT": 3,
        "SUSPECTED": 2,
        "PRODDED": 1,
        "RECORD": 1,
        "UPSETTING": 1,
        "FRUIT": 1,
        "CART": 1,
        "JACKDAWS": 1,
        "KNOCKED": 1,
        "RUSH": 1,
        "WINGS": 1,
        "BEAKS": 1,
        "CLAWS": 2,
        "THREATENED": 2,
        "DAMAGE": 1,
        "BRILLIANT": 1,
        "PLATING": 1,
        "PICKED": 2,
        "AXE": 1,
        "WHIRL": 1,
        "SWIFTLY": 1,
        "AROUND": 2,
        "USE": 2,
        "CARRIES": 1,
        "JUDGE": 2,
        "WOOD": 3,
        "REAL": 2,
        "CLEVERNESS": 1,
        "APPROVINGLY": 1,
        "WONDER": 1,
        "BRAINS": 1,
        "COOLLY": 1,
        "THRONE": 1,
        "AMBLED": 1,
        "WOODEN": 1,
        "AFTERNOON": 1,
        "PARENT": 1,
        "DELIGHTEDLY": 1,
        "INVADING": 1,
        "ENTERED": 1,
        "SLOWLY": 1,
        "STOPPED": 1,
        "DIG": 1,
        "EMERALDS": 1,
        "WALLS": 2,
        "PAVING": 1,
        "STONES": 2,
        "POINTS": 1,
        "KNITTING": 1,
        "SOLDIER": 2,
        "REACHED": 1,
        "PALACE": 2,
        "SPREAD": 1,
        "CONQUERED": 1,
        "SCREAMING": 1,
        "MOUNTAINS": 3,
        "FOE": 1,
        "CRAWLED": 1,
        "SOFAS": 1,
        "ASSISTED": 2,
        "WOGGLE": 1,
        "BUG": 1,
        "HAVEN'T": 4,
        "PAINTED": 1,
        "THERE'S": 2,
        "SWALLOW": 1,
        "CONNECTED": 1,
        "CONTINUED": 2,
        "TERRIBLE": 1,
        "WEAPONS": 1,
        "INVADERS": 1,
        "MOMENT'S": 1,
        "LATE": 1,
        "TEAR": 2,
        "PIECES": 2,
        "SIGHED": 1,
        "EMERGENCY": 1,
        "PAUSE": 1,
        "REFLECT": 1,
        "GATHERING": 1,
        "HASTENING": 1,
        "ELIZABETH": 3,
        "MADAM": 1,
        "COLLINS": 3,
        "EXCUSE": 1,
        "ANYBODY": 1,
        "NEED": 1,
        "GOING": 5,
        "MISSUS": 4,
        "BENNET": 1,
        "UNLUCKY": 1,
        "CARRIAGE": 2,
        "JANE": 4,
        "HORSEBACK": 1,
        "LIKELY": 1,
        "SCHEME": 1,
        "APPLICATION": 1,
        "ENCOURAGE": 1,
        "CONSISTENT": 1,
        "DELICACY": 2,
        "FEMALE": 2,
        "CHARACTER": 1,
        "REALLY": 3,
        "WARMTH": 1,
        "PUZZLE": 1,
        "EXCEEDINGLY": 1,
        "LIKED": 3,
        "HEART": 5,
        "SMART": 1,
        "YOUNG": 2,
        "COLONEL": 3,
        "THOUSAND": 1,
        "YEAR": 5,
        "GIRLS": 1,
        "NAY": 1,
        "FORSTER": 2,
        "BECOMING": 1,
        "WILLIAM'S": 1,
        "REGIMENTALS": 1,
        "MAMMA": 1,
        "LYDIA": 1,
        "AUNT": 1,
        "SAYS": 2,
        "CARTER": 1,
        "WATSON'S": 1,
        "BINGLEY": 2,
        "MANNERS": 1,
        "PRONOUNCED": 1,
        "MIXTURE": 1,
        "PRIDE": 1,
        "IMPERTINENCE": 1,
        "STYLE": 2,
        "HURST": 1,
        "ADDED": 4,
        "PAY": 2,
        "COMPLIMENT": 1,
        "BELIEVING": 1,
        "WISH": 2,
        "REFUSING": 1,
        "PREVENT": 1,
        "MAKING": 5,
        "OFFER": 1,
        "SATISFIED": 1,
        "FEELINGS": 1,
        "REGARD": 1,
        "PARTICULAR": 4,
        "ADVICE": 1,
        "RECOMMENDATION": 1,
        "HONOUR": 1,
        "CALLING": 4,
        "PATRONESS": 1,
        "CONDESCENDED": 1,
        "OPINION": 2,
        "ADVISABLE": 1,
        "STATE": 3,
        "REASONS": 1,
        "MARRYING": 1,
        "MOREOVER": 1,
        "COMING": 5,
        "HERTFORDSHIRE": 1,
        "DESIGN": 1,
        "SELECTING": 1,
        "CERTAINLY": 3,
        "SOLEMN": 1,
        "COMPOSURE": 1,
        "EAGERLY": 1,
        "DAUGHTER": 1,
        "READ": 3,
        "HASTE": 2,
        "LOVE": 2,
        "ALOUD": 1,
        "CONSIDER": 1,
        "ELEGANT": 1,
        "INTENDING": 1,
        "PLAGUE": 1,
        "RATIONAL": 1,
        "CREATURE": 1,
        "SPEAKING": 3,
        "TRUTH": 3,
        "UNIFORMLY": 1,
        "CHARMING": 1,
        "AWKWARD": 1,
        "GALLANTRY": 1,
        "PALTRY": 1,
        "UNDOUBTEDLY": 1,
        "DARCY": 1,
        "REMARK": 1,
        "MEANNESS": 1,
        "ARTS": 1,
        "LADIES": 1,
        "CONDESCEND": 1,
        "EMPLOY": 1,
        "CAPTIVATION": 1,
        "QUESTION": 2,
        "ARISE": 1,
        "BLESSINGS": 1,
        "CHRISTIANITY": 1,
        "DISTINCT": 1,
        "CIVILIZATION": 2,
        "SWAYS": 1,
        "RUNS": 1,
        "CHILDREN": 5,
        "GULF": 1,
        "FIXED": 1,
        "SPRING": 2,
        "ACROSS": 2,
        "ENORMOUS": 2,
        "SAFE": 2,
        "PLACE": 4,
        "BEREA": 1,
        "DURBAN": 1,
        "WRITING": 1,
        "SUGGEST": 1,
        "TOUCHES": 1,
        "KINSHIP": 1,
        "FUNDAMENTAL": 1,
        "PRINCIPLES": 1,
        "IDENTICAL": 1,
        "LAUGH": 1,
        "CHURCHYARD": 1,
        "FEELING": 2,
        "EGOTISTICAL": 1,
        "TALK": 2,
        "FETCHED": 1,
        "BOAT": 1,
        "SOUTHAMPTON": 1,
        "SWELL": 1,
        "TURNS": 1,
        "CONTINUALLY": 1,
        "PATTERNS": 1,
        "COMBINATIONS": 1,
        "COMPOSING": 1,
        "ELEMENTS": 1,
        "REMAIN": 1,
        "ALLAN": 1,
        "QUATERMAIN": 1,
        "RIDER": 2,
        "HAGGARD": 2,
        "INSCRIBE": 1,
        "ADVENTURE": 2,
        "SON": 4,
        "ARTHUR": 1,
        "STRIKE": 1,
        "WHILST": 1,
        "ENJOYING": 1,
        "MARVELLOUS": 1,
        "DISH": 1,
        "SAVAGE": 1,
        "HENRY": 2,
        "SOLOMON'S": 1,
        "HOBBLING": 1,
        "FAINT": 1,
        "SIDE": 5,
        "POWERS": 1,
        "DISPERSED": 1,
        "HASTY": 1,
        "SUPPOSED": 1,
        "ASSASSINS": 1,
        "RAZED": 1,
        "FLOURISHING": 1,
        "DESERT": 1,
        "DOWAGER": 2,
        "CZARINA": 3,
        "FORCED": 1,
        "CONVENT": 2,
        "ASHAMED": 2,
        "APPEAR": 1,
        "SEND": 2,
        "MASTER": 4,
        "REMAINED": 2,
        "CHEST": 1,
        "HENCEFORTH": 1,
        "FREED": 1,
        "TROUBLE": 2,
        "BOUNTIFULLY": 1,
        "GOODS": 1,
        "RENDERED": 3,
        "ASSISTANCE": 1,
        "LOUIS": 3,
        "ALMOST": 2,
        "TOWNS": 1,
        "CITIES": 1,
        "AUTHORITY": 1,
        "OBEDIENCE": 1,
        "RULE": 1,
        "FORMIDABLE": 1,
        "TEST": 1,
        "UNDERGONE": 1,
        "FORSOOK": 1,
        "INTENSE": 1,
        "RECOGNIZED": 2,
        "SITUATION": 1,
        "RESPECTFULLY": 1,
        "CONDUCTED": 1,
        "WALKING": 1,
        "BARE": 1,
        "HEADED": 1,
        "CAPITAL": 1,
        "ATTENTION": 1,
        "ACTING": 1,
        "OPPOSITION": 1,
        "SAVE": 2,
        "INSTEAD": 1,
        "ALLOWING": 1,
        "DULY": 1,
        "SUCCEED": 1,
        "POSSESSION": 1,
        "ELECTORATE": 1,
        "INVESTED": 1,
        "INQUIRED": 1,
        "LEARNT": 2,
        "FROGS": 1,
        "CROAK": 1,
        "DENMARK": 1,
        "SINGULARLY": 1,
        "ENOUGH": 3,
        "NAMED": 1,
        "VOLDEMAR": 1,
        "POTENTATES": 1,
        "EQUALLY": 1,
        "DESIROUS": 1,
        "NEIGHBOUR'S": 1,
        "AFFAIRS": 2,
        "FIELD": 2,
        "CHAPEL": 1,
        "DU": 1,
        "ESPRIT": 1,
        "SEPULTURE": 1,
        "ABSENT": 1,
        "ELECTOR": 1,
        "UNCONSCIOUS": 1,
        "EVENT": 1,
        "QUICKLY": 1,
        "NOISED": 1,
        "SUDDEN": 1,
        "TWELVE": 3,
        "OUTLINED": 1,
        "SURFACE": 4,
        "AREA": 1,
        "SLICE": 1,
        "ICE": 2,
        "METER": 1,
        "THICK": 2,
        "HUNDRED": 3,
        "CUBIC": 1,
        "METERS": 2,
        "ASSUMING": 1,
        "NAUTILUS'S": 2,
        "CHIEF": 5,
        "SUPERVISED": 1,
        "STRUCK": 1,
        "UNUSUALLY": 1,
        "WARMED": 2,
        "PROMPTLY": 1,
        "WIELDING": 1,
        "PICK": 2,
        "MOVEMENTS": 2,
        "FREE": 1,
        "ALTHOUGH": 1,
        "EXECUTED": 1,
        "PRESSURE": 1,
        "THIRTY": 3,
        "ATMOSPHERES": 1,
        "JELLYFISH": 1,
        "SHAPED": 1,
        "SMOOTH": 1,
        "SEMISPHERIC": 1,
        "PARASOLS": 1,
        "RUSSET": 1,
        "STRIPES": 1,
        "FRINGES": 1,
        "NEAT": 1,
        "FESTOONS": 1,
        "NAUTILUS": 2,
        "ROSE": 2,
        "NOON": 2,
        "RAISED": 1,
        "WEST": 1,
        "NOTED": 1,
        "CLOSING": 1,
        "LIQUID": 1,
        "STRATA": 1,
        "FARTHEST": 1,
        "TRENCH": 1,
        "WORKMEN": 1,
        "TOOLS": 1,
        "SHOWING": 2,
        "TENDENCY": 1,
        "SOLIDIFY": 1,
        "IMMINENT": 1,
        "THEY'LL": 1,
        "SUPPLY": 1,
        "WE'VE": 2,
        "BURIED": 1,
        "BENEATH": 1,
        "ATMOSPHERE": 1,
        "NEEDS": 1,
        "RENEWING": 1,
        "FORTY": 1,
        "RESERVE": 1,
        "WATERWAYS": 1,
        "NETS": 1,
        "SAMPLES": 1,
        "ALGAE": 1,
        "FUCUS": 1,
        "PLANTS": 1,
        "ROOTS": 1,
        "LADEN": 1,
        "WORLD'S": 1,
        "MUSSELS": 1,
        "EQUIPMENT": 1,
        "REENTERED": 1,
        "FOUL": 1,
        "BOARD": 3,
        "UNFLINCHING": 1,
        "UNCOMPLAINING": 1,
        "ENERGY": 1,
        "MONITORED": 1,
        "OPERATION'S": 1,
        "PROGRESS": 1,
        "DOUBLE": 1,
        "CHECKING": 1,
        "INSPECTIONS": 1,
        "IT'S": 1,
        "WORKING": 1,
        "ESCAPED": 1,
        "CRUSHED": 2,
        "ASPHYXIATION": 2,
        "CHUNKS": 1,
        "WEIGHED": 1,
        "LESS": 3,
        "UNUSUAL": 1,
        "SPECIFIC": 1,
        "CHUNK": 1,
        "WING": 1,
        "ROOF": 1,
        "TUNNEL": 1,
        "EVERYONE": 3,
        "DOOMED": 1,
        "PERISH": 1,
        "TOMB": 1,
        "DREADFUL": 1,
        "LAPSE": 1,
        "BANALITY": 1,
        "CONSEIL": 1,
        "HANGING": 2,
        "SCHOOLFELLOW": 1,
        "BELIEVE": 3,
        "HURT": 1,
        "BOILING": 1,
        "FERFITCHKIN": 1,
        "ROUGHLY": 1,
        "TERMS": 2,
        "ZVERKOV": 2,
        "TRUDOLYUBOV": 1,
        "FROWNING": 1,
        "SUBLIME": 1,
        "MANFRED": 1,
        "KISS": 1,
        "WEEP": 1,
        "COUNTLESS": 1,
        "MILLIONS": 1,
        "IMMEDIATELY": 3,
        "HUMANITY": 1,
        "CONFESSED": 1,
        "SHAMEFUL": 2,
        "DEEDS": 1,
        "MERELY": 1,
        "PRETTY": 1,
        "PLAYFUL": 1,
        "LESSONS": 1,
        "WORSE": 2,
        "CERTIFICATE": 1,
        "POWERFUL": 1,
        "INTERESTS": 2,
        "SCHOOL": 2,
        "ESTATE": 1,
        "SERFS": 1,
        "STOLE": 1,
        "BRUSHES": 1,
        "CLEAN": 1,
        "DETECT": 1,
        "CONTEMPT": 1,
        "CRAVING": 1,
        "SOCIETY": 1,
        "DEVELOPED": 1,
        "ATTEMPTED": 2,
        "FRIENDLY": 1,
        "SCHOOLFELLOWS": 1,
        "SOMEHOW": 2,
        "INTIMACY": 1,
        "STRAINED": 1,
        "ENDED": 1,
        "DISTANT": 2,
        "RELATIONS": 1,
        "DEPENDENT": 1,
        "FORLORN": 1,
        "SILENT": 2,
        "REPROACHES": 1,
        "DOUBT": 2,
        "PERFECTLY": 2,
        "MONSTROUSLY": 1,
        "EXAGGERATING": 1,
        "FACTS": 1,
        "REFLECTIONS": 1,
        "IMPELLED": 1,
        "PURPOSELY": 1,
        "TAKEN": 1,
        "COMPROMISING": 1,
        "INSIGNIFICANT": 1,
        "THEATRE": 1,
        "TIER": 1,
        "DOMINATING": 1,
        "CARRYING": 2,
        "ELEVATION": 1,
        "WIT": 1,
        "ABANDON": 1,
        "EXTERNAL": 1,
        "CIRCUMSTANCE": 1,
        "EXPAND": 1,
        "VISTA": 1,
        "ACTIVITY": 3,
        "BENEFICENT": 1,
        "ABOVE": 2,
        "READY": 4,
        "CORPULENT": 1,
        "SUBSCRIPTION": 1,
        "ASK": 4,
        "MUTTERED": 2,
        "EMBARRASSMENT": 1,
        "FLUSHED": 1,
        "CRIMSON": 1,
        "REMEMBERED": 1,
        "OWED": 1,
        "SIMONOV": 1,
        "ROUBLES": 1,
        "EMBARRASSED": 1,
        "KENNICOTT'S": 1,
        "FRANKNESS": 1,
        "AGREED": 1,
        "INSANE": 1,
        "CONDITION": 1,
        "FARMERS": 2,
        "SLEIGHS": 1,
        "QUILTS": 1,
        "HAY": 1,
        "PILED": 1,
        "FUR": 5,
        "COATS": 1,
        "CAPS": 1,
        "MITTENS": 2,
        "OVERSHOES": 1,
        "BUCKLING": 1,
        "GRAY": 1,
        "KNITTED": 1,
        "SCARFS": 1,
        "TEN": 1,
        "WOOLEN": 1,
        "SOCKS": 1,
        "TAR": 2,
        "BAGS": 1,
        "CLOSETS": 1,
        "SMALL": 1,
        "BOYS": 1,
        "SQUEALING": 1,
        "PACKS": 1,
        "DIVISION": 1,
        "PANTING": 1,
        "SUMMER": 1,
        "STINGING": 1,
        "WINTER": 2,
        "NORTHERN": 1,
        "PLAINS": 1,
        "REDISCOVERED": 1,
        "SURPRISE": 1,
        "HEROISM": 1,
        "ARMOR": 1,
        "ARTIC": 1,
        "EXPLORER": 1,
        "GARMENTS": 1,
        "SURPASSED": 1,
        "GOSSIP": 1,
        "TOPIC": 1,
        "PARTIES": 1,
        "FORM": 2,
        "HEAVIES": 1,
        "YOU'RE": 4,
        "ORGANIZING": 1,
        "DEPRIVE": 1,
        "TOWNSMEN": 1,
        "MORTGAGES": 1,
        "WHEAT": 2,
        "SHOPS": 1,
        "WE'RE": 2,
        "WAR": 1,
        "GERMANY": 1,
        "DOESN'T": 1,
        "PRO": 1,
        "GERMAN": 1,
        "THEY'D": 1,
        "SKIING": 1,
        "EXPEDITION": 1,
        "JOLLILY": 1,
        "THEREAFTER": 1,
        "MANUALS": 1,
        "BRIDGE": 1,
        "CAROL": 2,
        "DISCOURAGED": 1,
        "GRATEFUL": 1,
        "KENNICOTT": 1,
        "INVITED": 1,
        "RABBIT": 1,
        "HUNTING": 1,
        "WOODS": 1,
        "AUTUMN": 1,
        "WAKAMIN": 1,
        "SHERIFF": 2,
        "FORBIDDEN": 1,
        "ORGANIZER": 2,
        "NATIONAL": 1,
        "NONPARTISAN": 1,
        "LEAGUE": 1,
        "ANYWHERE": 2,
        "COUNTY": 1,
        "DEFIED": 1,
        "YOURSELF": 2,
        "I'M": 2,
        "DAMNED": 1,
        "I'LL": 3,
        "AGREE": 1,
        "FREAK": 1,
        "NOTIONS": 1,
        "DEPEND": 1,
        "FLATLY": 1,
        "ELEPHANTS": 1,
        "GOLDEN": 5,
        "HOWDAHS": 1,
        "PEEP": 1,
        "MAHARANEES": 1,
        "NECKLACES": 1,
        "RUBIES": 1,
        "DAWN": 1,
        "COLORED": 1,
        "CALLS": 1,
        "SHINY": 1,
        "FLORAL": 1,
        "STEEL": 1,
        "TIPPED": 1,
        "CUTTER": 1,
        "RUDDY": 1,
        "NOSE": 1,
        "CIGAR": 1,
        "EMERGING": 1,
        "STIRRED": 1,
        "MAIN": 1,
        "LOOSE": 1,
        "NUTRIA": 1,
        "TIPS": 1,
        "LOVED": 1,
        "SILKEN": 1,
        "MIND": 4,
        "TELLING": 1,
        "LIFETIME": 1,
        "TICKLED": 1,
        "SELL": 1,
        "PRACTISE": 1,
        "SAT": 1,
        "RICKETY": 1,
        "DESK": 2,
        "LIVING": 1,
        "POEM": 1,
        "FARTHER": 1,
        "SKY": 4,
        "SUN": 1,
        "WARM": 2,
        "NE'ER": 1,
        "STRAIGHT": 2,
        "INTERRUPTION": 1,
        "DECEIVE": 1,
        "EARS": 3,
        "MULTITUDE": 1,
        "SEDUCTIVE": 2,
        "ARGUMENTS": 1,
        "PASS": 2,
        "REFUTATION": 1,
        "THRACE": 2,
        "RETIRE": 1,
        "FIGHTING": 1,
        "GATES": 1,
        "SHUT": 2,
        "MARCH": 2,
        "CARELESSLY": 1,
        "NOTICING": 1,
        "SUCCESSFUL": 1,
        "DETECTS": 1,
        "BLUNDER": 1,
        "CHANCE": 1,
        "ESTABLISHING": 1,
        "PANIC": 1,
        "ASSAILANT": 1,
        "TERRORS": 1,
        "ENGAGED": 2,
        "BRAVE": 1,
        "SPARTAN": 1,
        "KINDRED": 1,
        "UTTERLY": 1,
        "IRRATIONAL": 1,
        "ATHENIANS": 1,
        "CASES": 1,
        "RUSHING": 1,
        "DISGRACE": 1,
        "MERE": 2,
        "INFLUENCE": 1,
        "DESPISING": 1,
        "SCANTY": 1,
        "NUMBERS": 1,
        "OPPONENT": 1,
        "AMPHIPOLIS": 1,
        "FORCE": 1,
        "LOCRIAN": 1,
        "SETTLERS": 1,
        "EXILED": 1,
        "MESSINA": 2,
        "THITHER": 1,
        "LOCRIANS": 1,
        "FACTIONS": 1,
        "DIVIDED": 1,
        "PACIFICATION": 1,
        "SICILY": 1,
        "STAKED": 1,
        "TRUSTED": 1,
        "FLOWER": 1,
        "ATHENIAN": 1,
        "LEMNIANS": 1,
        "IMBRIANS": 1,
        "PREPARED": 1,
        "ASSAIL": 1,
        "STRATAGEM": 1,
        "TROOPS": 1,
        "SHIFTS": 1,
        "REMAINING": 1,
        "LEADS": 1,
        "BLESS": 1,
        "SIMPLICITY": 1,
        "ENVY": 1,
        "FOLLY": 1,
        "LACEDAEMONIANS": 1,
        "COUNTRY'S": 1,
        "LAWS": 1,
        "ENVOYS": 1,
        "PERDICCAS": 1,
        "COMMAND": 1,
        "ATTENDANCE": 1,
        "ALLIANCE": 1,
        "HUNGER": 1,
        "PLANE": 1,
        "PLANKS": 1,
        "COFFINS": 1,
        "PEACE": 1,
        "STEPMOTHER": 1,
        "GRETEL": 7,
        "WEPT": 1,
        "BITTER": 1,
        "HANSEL": 6,
        "TIRED": 1,
        "SLEEP": 1,
        "FOREST": 3,
        "CUT": 2,
        "FETCH": 2,
        "WROTE": 1,
        "ADDRESS": 1,
        "STEADY": 1,
        "WRITE": 1,
        "POULTERER'S": 1,
        "KEEN": 1,
        "SCENT": 1,
        "BEASTS": 1,
        "AWARE": 1,
        "HUMAN": 2,
        "BEINGS": 1,
        "NEIGHBOURHOOD": 1,
        "LAUGHED": 1,
        "MALICE": 1,
        "MOCKINGLY": 1,
        "BEDPOST": 1,
        "HAPPIEST": 1,
        "BREAD": 1,
        "INTENDED": 2,
        "OVEN": 1,
        "BAKE": 1,
        "EAT": 2,
        "WOMAN": 3,
        "EMPTIED": 1,
        "PINAFORE": 1,
        "PEARLS": 1,
        "PRECIOUS": 1,
        "HANDFUL": 1,
        "POCKET": 1,
        "ADD": 1,
        "SCROOGE": 1,
        "LEAPING": 1,
        "STOOL": 1,
        "YOURSELVES": 1,
        "SCOLDED": 1,
        "LIKEWISE": 1,
        "SECOND": 2,
        "AWAKE": 1,
        "FOLKS": 1,
        "ASLEEP": 1,
        "PEBBLES": 1,
        "SLID": 3,
        "SEIZED": 1,
        "HOLD": 1,
        "HUGE": 1,
        "TORE": 1,
        "STAMPED": 1,
        "TUMULT": 1,
        "WON": 1,
        "FISHES": 1,
        "EELS": 1,
        "ARBOURS": 1,
        "GODS": 9,
        "DOMINION": 1,
        "INNERMOST": 1,
        "SACRED": 1,
        "RECESSES": 1,
        "HILLS": 2,
        "TROOPED": 1,
        "TOED": 1,
        "BALL": 5,
        "GENTLY": 1,
        "DAWNCHILD": 2,
        "GLEAM": 1,
        "ONYX": 1,
        "STEP": 1,
        "PROFESSIONAL": 1,
        "CLAPTRAP": 1,
        "CARED": 1,
        "BECAME": 1,
        "OBLIGATION": 1,
        "DARNAY": 2,
        "QUARREL": 1,
        "STAIRWAY": 2,
        "CHIPPED": 1,
        "EDGES": 1,
        "LIMPANG": 1,
        "TUNG": 1,
        "TRAMP": 1,
        "ARMIES": 1,
        "SOUNDED": 1,
        "NEARER": 2,
        "DOWNLANDS": 2,
        "MARCHED": 1,
        "LINE": 1,
        "GLEAMING": 2,
        "CLIFFS": 1,
        "LENIENT": 1,
        "FAULTS": 1,
        "SELDOM": 1,
        "REVEALS": 1,
        "WOUNDS": 1,
        "BLEEDING": 1,
        "PAINFUL": 1,
        "REFLECTION": 1,
        "RIM": 1,
        "THEREAT": 1,
        "UMBORODOM": 1,
        "HOUND": 2,
        "THUNDER": 1,
        "LEASH": 1,
        "STRODE": 1,
        "LARGE": 2,
        "INSUFFERABLE": 1,
        "LIKING": 2,
        "FORGOT": 1,
        "BOUNDING": 1,
        "FLARING": 1,
        "LAUGHING": 1,
        "FIELDS": 1,
        "BELOW": 1,
        "DESTINED": 1,
        "GENUINE": 1,
        "TRUST": 1,
        "ASIDE": 1,
        "PURPOSE": 1,
        "INCAPABLE": 1,
        "FLIGHTS": 1,
        "STRYVER": 1,
        "HE'LL": 1,
        "SADDEST": 1,
        "DAWNCHILD'S": 1,
        "GRIEF": 1,
        "PLAY": 1,
        "SILVER": 3,
        "MOON": 1,
        "SOUTH": 1,
        "WIND": 3,
        "CRY": 1,
        "NORTH": 2,
        "WINDS": 1,
        "SERIOUS": 1,
        "EXPECTORATIVE": 1,
        "CONTEMPLATION": 1,
        "BOOT": 1,
        "COLUMN": 1,
        "WEIRD": 1,
        "BAPTISM": 1,
        "NERVOUS": 1,
        "LOAD": 1,
        "MILD": 1,
        "PRESENCE": 1,
        "DIANA": 1,
        "ENDYMION": 1,
        "SPLENDOR": 1,
        "CAVERN": 2,
        "VEHICLE": 1,
        "SEAT": 1,
        "WOMAN'S": 1,
        "HAIRPIN": 1,
        "GUY": 1,
        "DISPOSED": 1,
        "RULING": 1,
        "IMPROPER": 1,
        "UNCOMFORTABLY": 1,
        "ENERGETIC": 1,
        "SEPARATE": 1,
        "FORMLESS": 1,
        "MASSES": 1,
        "SHADOWY": 1,
        "LANDSCAPE": 1,
        "TREES": 1,
        "ISOLATED": 1,
        "CLUMPS": 1,
        "ASSEMBLAGES": 1,
        "CHANGED": 1,
        "PLACES": 1,
        "OUTLINES": 1,
        "TONIGHT": 1,
        "NORMALLY": 1,
        "CONFIDANT": 1,
        "PLAYS": 1,
        "TIRING": 1,
        "MIRROR": 1,
        "LOYAL": 1,
        "GROWING": 1,
        "ACCUSTOMED": 1,
        "DARKNESS": 1,
        "MC": 1,
        "GANUM": 1,
        "SHE'S": 2,
        "STOLID": 1,
        "WESTLAKE": 1,
        "NOBODY": 1,
        "SWEETER": 1,
        "BLAND": 1,
        "CONFIDE": 1,
        "SAVORLESS": 1,
        "PROUD": 1,
        "TREMENDOUSLY": 1,
        "TWENTY": 1,
        "HEXES": 1,
        "WHISPERING": 1,
        "IMPULSIVELY": 1,
        "VILLAGE": 1,
        "VIRUS": 1,
        "SOUNDS": 1,
        "DANGEROUS": 2,
        "CANCER": 1,
        "FIFTY": 1,
        "UNLESS": 1,
        "STOP": 1,
        "SMOKING": 1,
        "TROUBLES": 1,
        "UNNECESSARY": 1,
        "BEATEN": 1,
        "GROW": 1,
        "KEEP": 1,
        "SENDS": 1,
        "BLIZZARDS": 1,
        "RAISE": 1,
        "DEVIL": 1,
        "WARS": 1,
        "POLITICS": 1,
        "RACE": 1,
        "HATREDS": 1,
        "LABOR": 1,
        "DISPUTES": 1,
        "WONDERED": 2,
        "OUGHT": 1,
        "OFFENDED": 1,
        "CARESS": 1,
        "HAT": 1,
        "ORIENTAL": 1,
        "TURBAN": 1,
        "BROCADE": 1,
        "DROPPED": 1,
        "ELBOW": 1,
        "BRUSHED": 1,
        "SHOULDER": 1,
        "FLITTED": 1,
        "CHAIR": 1,
        "STOOPED": 1,
        "DETECTED": 1,
        "RELIEVED": 1,
        "OCCURRED": 1,
        "WINGDAM": 1,
        "SLUMGULLION": 1,
        "BANDITTI": 1,
        "LICENSED": 1,
        "HOTELKEEPERS": 1,
        "ATROCIOUS": 1,
        "ALLUSIVENESS": 1,
        "INSPECTOR": 4,
        "HEAT": 2,
        "FACING": 1,
        "GAS": 1,
        "LAMP": 1,
        "YAWNED": 1,
        "DEALER": 1,
        "GLOOM": 1,
        "AVENUE": 1,
        "BIZARRE": 1,
        "WARDROBES": 1,
        "UNDERGROWTH": 1,
        "TANGLE": 1,
        "TABLE": 1,
        "MISSED": 1,
        "POSTAGE": 1,
        "TRAINED": 1,
        "FACULTIES": 1,
        "CEASED": 2,
        "CONSTABLE": 2,
        "TONE": 1,
        "ASSISTANT": 1,
        "COMMISSIONER'S": 1,
        "REMARKS": 1,
        "SOUR": 1,
        "TEETH": 1,
        "MANAGED": 1,
        "STARTING": 1,
        "BEGIN": 1,
        "INVESTIGATION": 1,
        "SPOT": 1,
        "FAIR": 2,
        "SLIGHT": 3,
        "OUTRAGE": 1,
        "WEEK": 1,
        "ASSURED": 1,
        "OFFICIAL": 1,
        "OUTBREAK": 1,
        "ANARCHIST": 1,
        "APPREHENDED": 1,
        "SUFFICIENTLY": 1,
        "ANNOYING": 1,
        "STATEMENT": 1,
        "CHAP": 2,
        "VARNISH": 1,
        "UNHAPPY": 1,
        "HOMELESS": 1,
        "COUCH": 1,
        "ACCOMPANIED": 1,
        "UNRELATED": 1,
        "ALLEY": 1,
        "STALWART": 1,
        "ERECT": 1,
        "OPPOSITE": 1,
        "DIRECTION": 2,
        "SIMPLY": 1,
        "UNDERSTANDING": 1,
        "FUNNY": 1,
        "VELVET": 3,
        "COLLAR": 3,
        "MISTAKE": 1,
        "COMPLETE": 1,
        "CONVICTIONS": 1,
        "OPPORTUNITY": 1,
        "FAVOURABLE": 1,
        "HUMANE": 1,
        "MOVE": 1,
        "QUALITY": 1,
        "SERIOUSNESS": 1,
        "BELONGING": 1,
        "SPORT": 1,
        "RID": 1,
        "SEVEN": 1,
        "SHOWED": 1,
        "SWABS": 1,
        "IMPORTANCE": 1,
        "THREADS": 1,
        "THICKER": 1,
        "SPIDER'S": 1,
        "SHORE": 1,
        "SMELL": 1,
        "DEAL": 1,
        "SPIRIT": 1,
        "WEREN'T": 1,
        "STAGE": 2,
        "AWAKENED": 1,
        "PUNCH": 1,
        "RIBS": 1,
        "OPENED": 1,
        "STANDING": 1,
        "BUILDING": 1,
        "SUITS": 1,
        "TRUMP": 1,
        "DECLARED": 1,
        "SQUIRE": 2,
        "JIM": 1,
        "ARMCHAIR": 1,
        "BAR": 1,
        "APPRENTICE": 1,
        "ERE": 1,
        "PLANS": 1,
        "LIVESEY'S": 1,
        "KEEPING": 1,
        "CARRIED": 1,
        "LITERALLY": 1,
        "SLAVED": 1,
        "BRISTOL": 1,
        "PORT": 1,
        "SAILED": 1,
        "REDRUTH": 1,
        "INTERRUPTING": 1,
        "LETTER": 1,
        "BOX": 1,
        "WHISPERED": 1,
        "MYSTERIOUS": 1,
        "INDIGNATION": 1,
        "MATTER": 1,
        "POSSIBLE": 2,
        "TREAT": 1,
        "UNWASHED": 1,
        "COUNTENANCE": 1,
        "FLAMED": 1,
        "POSTSCRIPT": 1,
        "BLANDLY": 2,
        "CONSORT": 1,
        "TURN": 1,
        "AUGUST": 1,
        "SAILING": 1,
        "STIFF": 1,
        "REGRET": 1,
        "SITTING": 1,
        "HOUSEKEEPER'S": 1,
        "ISLAND": 1,
        "FANCY": 1,
        "EXPLORED": 1,
        "ACRE": 1,
        "ATTEMPTS": 1,
        "COMMENTARY": 1,
        "HISPANIOLA": 1,
        "MANAGEMENT": 1,
        "MEREST": 1,
        "TRIFLE": 1
    },
    "duration_per_book_min": {
        "46": 0.653,
        "54": 2.929,
        "59": 0.841,
        "84": 2.615,
        "98": 0.921,
        "120": 3.291,
        "421": 0.546,
        "501": 1.743,
        "543": 4.449,
        "600": 2.761,
        "708": 1.719,
        "711": 1.592,
        "764": 1.381,
        "964": 0.881,
        "972": 2.291,
        "974": 2.659,
        "1184": 2.56,
        "1312": 0.998,
        "1342": 2.856,
        "1727": 2.244,
        "1989": 0.661,
        "2166": 0.836,
        "2439": 0.715,
        "2488": 2.642,
        "2591": 2.887,
        "2600": 1.457,
        "5788": 1.092,
        "5921": 1.609,
        "6763": 2.519,
        "6917": 0.658,
        "7142": 2.58,
        "8183": 1.809,
        "10869": 1.092,
        "11138": 0.361,
        "34181": 0.717,
        "35710": 1.692
    },
    "book distribution": {
        "1184": 13,
        "84": 13,
        "1989": 4,
        "10869": 8,
        "6917": 3,
        "972": 22,
        "34181": 3,
        "708": 7,
        "2439": 3,
        "6763": 11,
        "5921": 11,
        "964": 5,
        "421": 3,
        "764": 6,
        "120": 15,
        "5788": 5,
        "2600": 7,
        "11138": 2,
        "501": 9,
        "59": 4,
        "1727": 13,
        "54": 14,
        "1342": 12,
        "711": 7,
        "2166": 5,
        "35710": 9,
        "2591": 12,
        "2488": 13,
        "600": 14,
        "543": 19,
        "7142": 13,
        "46": 3,
        "8183": 9,
        "98": 4,
        "1312": 5,
        "974": 14
    },
    "chapter distribution": {
        "121024": 13,
        "369": 8,
        "368": 5,
        "121721": 4,
        "47824": 8,
        "124588": 3,
        "129390": 12,
        "129385": 10,
        "87733": 3,
        "183930": 7,
        "132799": 3,
        "124002": 2,
        "124003": 3,
        "123998": 6,
        "293987": 2,
        "122255": 5,
        "127786": 9,
        "162375": 3,
        "148920": 6,
        "287139": 4,
        "128411": 5,
        "132011": 5,
        "140215": 2,
        "29350": 2,
        "126865": 5,
        "126864": 4,
        "124400": 4,
        "121534": 6,
        "121535": 7,
        "125945": 3,
        "125943": 2,
        "125941": 6,
        "125951": 3,
        "1129": 6,
        "1119": 4,
        "1120": 2,
        "133630": 7,
        "128761": 5,
        "84340": 3,
        "126320": 3,
        "84333": 6,
        "130894": 9,
        "130895": 4,
        "123720": 10,
        "123719": 4,
        "124520": 7,
        "124549": 5,
        "126961": 5,
        "126959": 8,
        "126296": 9,
        "289453": 3,
        "127731": 4,
        "127732": 5,
        "128329": 4,
        "143022": 5,
        "124526": 7,
        "126734": 13,
        "127518": 11,
        "126737": 1
    },
    "duration_per_chapter_min": {
        "368": 0.956,
        "369": 1.659,
        "1119": 0.965,
        "1120": 0.501,
        "1129": 1.39,
        "29350": 0.144,
        "47824": 1.092,
        "84333": 1.072,
        "84340": 0.621,
        "87733": 0.717,
        "121024": 2.56,
        "121534": 0.877,
        "121535": 1.367,
        "121721": 0.661,
        "122255": 0.881,
        "123719": 0.725,
        "123720": 2.035,
        "123998": 1.483,
        "124002": 0.448,
        "124003": 0.588,
        "124400": 0.841,
        "124520": 1.682,
        "124526": 1.606,
        "124549": 1.161,
        "124588": 0.658,
        "125941": 1.188,
        "125943": 0.401,
        "125945": 0.711,
        "125951": 0.63,
        "126296": 2.181,
        "126320": 0.706,
        "126734": 2.417,
        "126737": 0.241,
        "126864": 0.801,
        "126865": 0.942,
        "126959": 1.528,
        "126961": 1.052,
        "127518": 2.5,
        "127731": 0.876,
        "127732": 0.933,
        "127786": 1.258,
        "128329": 0.921,
        "128411": 1.092,
        "128761": 0.836,
        "129385": 0.99,
        "129390": 1.301,
        "130894": 1.931,
        "130895": 0.711,
        "132011": 1.313,
        "132799": 0.715,
        "133630": 1.592,
        "140215": 0.361,
        "143022": 0.998,
        "148920": 1.381,
        "162375": 0.546,
        "183930": 1.719,
        "287139": 0.792,
        "289453": 0.653,
        "293987": 0.351
    }
}